{
  "metadata": {
    "fetched_at": "2025-12-04T01:11:41.661322",
    "source": "https://ppv.to/api/streams",
    "total_events": null,
    "m3u8_extraction": {
      "extracted_at": "2025-12-04T02:20:57.788283",
      "total_streams": 76,
      "streams_with_m3u8": 76,
      "success_rate": "100.0%",
      "extraction_stats": {
        "total_requests": 76,
        "successful_requests": 76,
        "failed_requests": 3,
        "elapsed_time_seconds": 205.86
      }
    }
  },
  "events": {
    "success": true,
    "timestamp": 1764810710,
    "READ_ME": "Interested in using our API? Contact us for more information.",
    "performance": 0.024796009063720703,
    "streams": [
      {
        "category": "Basketball",
        "id": 37,
        "always_live": false,
        "streams": [
          {
            "id": 14480,
            "name": "Portland Trail Blazers vs. Cleveland Cavaliers",
            "tag": "FDSNOH",
            "poster": "https://ppv.to/assets/thumb/d1ddc3c858d7bbe52b4c3cb09bac80f7-thumbnail.jpg",
            "blurhash": "LBEc9O}BRPwcsooLj[WV0{JRtRSh",
            "colors": [
              "#d53034",
              "#8b0a40"
            ],
            "uri_name": "nba/12-03-2025/por-cle",
            "starts_at": 1764806400,
            "ends_at": 1764816480,
            "always_live": 0,
            "locale": "en",
            "category_name": "Basketball",
            "iframe": "https://embednow.top/embed/nba/12-03-2025/por-cle",
            "viewers": "75",
            "substreams": [],
            "m3u8_url": "https://gg.poocloud.in/nba_clevelandcavaliers/index.m3u8",
            "m3u8_extracted_at": "2025-12-04T02:17:32.436632"
          },
          {
            "id": 14481,
            "name": "Denver Nuggets vs. Indiana Pacers",
            "tag": "FDSNIN",
            "poster": "https://ppv.to/assets/thumb/fe7f1ce1508bdab8f92a5e07c80566a8-thumbnail.jpg",
            "blurhash": "L484Y=009F~UjsfPj[j[00~V-;4:",
            "colors": [
              "#041735",
              "#0d3769"
            ],
            "uri_name": "nba/12-03-2025/den-ind",
            "starts_at": 1764806400,
            "ends_at": 1764816480,
            "always_live": 0,
            "locale": "en",
            "category_name": "Basketball",
            "iframe": "https://embednow.top/embed/nba/12-03-2025/den-ind",
            "viewers": "130",
            "substreams": [],
            "m3u8_url": "https://gg.poocloud.in/nba_indianapacers/index.m3u8",
            "m3u8_extracted_at": "2025-12-04T02:17:34.402486"
          },
          {
            "id": 14482,
            "name": "San Antonio Spurs vs. Orlando Magic",
            "tag": "FDSNFL",
            "poster": "https://ppv.to/assets/thumb/aa07b81e57fd6bd84534b1797c1134df-thumbnail.jpg",
            "blurhash": "L45YjYq?Dmxma#axj[j[00tp-:N1",
            "colors": [
              "#404040",
              "#0d57b6"
            ],
            "uri_name": "nba/12-03-2025/sas-orl",
            "starts_at": 1764806400,
            "ends_at": 1764816480,
            "always_live": 0,
            "locale": "en",
            "category_name": "Basketball",
            "iframe": "https://embednow.top/embed/nba/12-03-2025/sas-orl",
            "viewers": "142",
            "substreams": [],
            "m3u8_url": "https://gg.poocloud.in/nba_orlandomagic/index.m3u8",
            "m3u8_extracted_at": "2025-12-04T02:17:36.335145"
          },
          {
            "id": 14483,
            "name": "LA Clippers vs. Atlanta Hawks",
            "tag": "FDSNSE-ATL",
            "poster": "https://ppv.to/assets/thumb/8cd9d8ef6066804530c9f2118d02adeb-thumbnail.jpg",
            "blurhash": "L8COC71wvgoeo2a|j[fj00|vtlR+",
            "colors": [
              "#090c35",
              "#c91a37"
            ],
            "uri_name": "nba/12-03-2025/lac-atl",
            "starts_at": 1764808200,
            "ends_at": 1764818280,
            "always_live": 0,
            "locale": "en",
            "category_name": "Basketball",
            "iframe": "https://embednow.top/embed/nba/12-03-2025/lac-atl",
            "viewers": "202",
            "substreams": [],
            "m3u8_url": "https://gg.poocloud.in/nba_atlantahawks/index.m3u8",
            "m3u8_extracted_at": "2025-12-04T02:17:38.189045"
          },
          {
            "id": 14484,
            "name": "Charlotte Hornets vs. New York Knicks",
            "tag": "MSG",
            "poster": "https://ppv.to/assets/thumb/dfeb53ea9e455ce94b22bef7ccc846cb-thumbnail.jpg",
            "blurhash": "L37n^D3g4.}j%2WXj[oL00{{?a5t",
            "colors": [
              "#006e81",
              "#274a8e"
            ],
            "uri_name": "nba/12-03-2025/cha-nyk",
            "starts_at": 1764808200,
            "ends_at": 1764818280,
            "always_live": 0,
            "locale": "en",
            "category_name": "Basketball",
            "iframe": "https://embednow.top/embed/nba/12-03-2025/cha-nyk",
            "viewers": "204",
            "substreams": [],
            "m3u8_url": "https://gg.poocloud.in/nba_newyorkknicks/index.m3u8",
            "m3u8_extracted_at": "2025-12-04T02:17:39.721303"
          },
          {
            "id": 14485,
            "name": "Brooklyn Nets vs. Chicago Bulls",
            "tag": "CHSN",
            "poster": "https://ppv.to/assets/thumb/b86624da8de6249e5f65ac4b0f1f2898-thumbnail.jpg",
            "blurhash": "L6D*Co4RVY9tbHoLj[WV00*zx]%M",
            "colors": [
              "#676767",
              "#d01b48"
            ],
            "uri_name": "nba/12-03-2025/bkn-chi",
            "starts_at": 1764810000,
            "ends_at": 1764820080,
            "always_live": 0,
            "locale": "en",
            "category_name": "Basketball",
            "iframe": "https://embednow.top/embed/nba/12-03-2025/bkn-chi",
            "viewers": "76",
            "substreams": [],
            "m3u8_url": "https://gg.poocloud.in/nba_chicagobulls/index.m3u8",
            "m3u8_extracted_at": "2025-12-04T02:17:41.754474"
          },
          {
            "id": 14486,
            "name": "Sacramento Kings vs. Houston Rockets",
            "tag": "SCHN",
            "poster": "https://ppv.to/assets/thumb/6c9a1b31189ab53495694ef34cfad333-thumbnail.jpg",
            "blurhash": "L7D7?%3sZ$0yn,a#j[j@00rBx]=|",
            "colors": [
              "#502376",
              "#cf1b48"
            ],
            "uri_name": "nba/12-03-2025/sac-hou",
            "starts_at": 1764810000,
            "ends_at": 1764820080,
            "always_live": 0,
            "locale": "en",
            "category_name": "Basketball",
            "iframe": "https://embednow.top/embed/nba/12-03-2025/sac-hou",
            "viewers": "149",
            "substreams": [],
            "m3u8_url": "https://gg.poocloud.in/nba_houstonrockets/index.m3u8",
            "m3u8_extracted_at": "2025-12-04T02:17:44.042900"
          },
          {
            "id": 14487,
            "name": "Detroit Pistons vs. Milwaukee Bucks",
            "tag": "FDSNWI",
            "poster": "https://ppv.to/assets/thumb/dcdeb3148bbbd2809e15abc80211801b-thumbnail.jpg",
            "blurhash": "L58EJJzlD*K%WBofj[WB00Ks-:z?",
            "colors": [
              "#143980",
              "#0c5125"
            ],
            "uri_name": "nba/12-03-2025/det-mil",
            "starts_at": 1764810000,
            "ends_at": 1764820080,
            "always_live": 0,
            "locale": "en",
            "category_name": "Basketball",
            "iframe": "https://embednow.top/embed/nba/12-03-2025/det-mil",
            "viewers": "280",
            "substreams": [],
            "m3u8_url": "https://gg.poocloud.in/nba_milwaukeebucks/index.m3u8",
            "m3u8_extracted_at": "2025-12-04T02:17:45.649541"
          },
          {
            "id": 14488,
            "name": "Miami Heat vs. Dallas Mavericks",
            "tag": "NBA TV",
            "poster": "https://ppv.to/assets/thumb/a8e908edb4259d33f1603c865a0da283-thumbnail.jpg",
            "blurhash": "L59Gn9_OM#?DxujZj[j@00Pq%fE3",
            "colors": [
              "#8d0025",
              "#0f6bb4"
            ],
            "uri_name": "nba/12-03-2025/mia-dal",
            "starts_at": 1764811800,
            "ends_at": 1764821880,
            "always_live": 0,
            "locale": "en",
            "category_name": "Basketball",
            "iframe": "https://embednow.top/embed/nba/12-03-2025/mia-dal",
            "viewers": "17",
            "substreams": [],
            "m3u8_url": "https://gg.poocloud.in/nba_dallasmavericks/index.m3u8",
            "m3u8_extracted_at": "2025-12-04T02:17:48.459547"
          }
        ]
      },
      {
        "category": "Combat Sports",
        "id": 33,
        "always_live": false,
        "streams": [
          {
            "id": 14282,
            "name": "UFC 323: Dvalishvili vs. Yan 2",
            "tag": "PPV",
            "poster": "https://ppv.to/assets/thumb/6381c559afa78de552235c103e13a74c-thumbnail.jpg",
            "blurhash": "LCF$Id-pxun%~Ws:IoRjD%RktQIp",
            "colors": [
              "#dbd5bb",
              "#d4cdb3"
            ],
            "uri_name": "ufc-323",
            "starts_at": 1765062000,
            "ends_at": 1765090800,
            "always_live": 0,
            "locale": "en",
            "category_name": "Combat Sports",
            "iframe": "https://embednow.top/embed/ufc-323",
            "viewers": "0",
            "substreams": [],
            "m3u8_url": "https://gg.poocloud.in/ufc/index.m3u8",
            "m3u8_extracted_at": "2025-12-04T02:17:50.652543"
          },
          {
            "id": 14283,
            "name": "UFC Fight Night: Royval vs. Kape",
            "tag": "ESPN",
            "poster": "https://ppv.to/assets/thumb/07e548c632b6de966682703f5478c806-thumbnail.jpg",
            "blurhash": "LGRKi*-jqZIt*7RoRWouQdNJeUxV",
            "colors": [
              "#e78d00",
              "#ffc700"
            ],
            "uri_name": "ufc-fight-night-royval-vs-kape",
            "starts_at": 1765681200,
            "ends_at": 1765702800,
            "always_live": 0,
            "locale": "en",
            "category_name": "Combat Sports",
            "iframe": "https://embednow.top/embed/ufc-fight-night-royval-vs-kape",
            "viewers": "0",
            "substreams": [],
            "m3u8_url": "https://gg.poocloud.in/ufc/index.m3u8",
            "m3u8_extracted_at": "2025-12-04T02:17:53.300801"
          },
          {
            "id": 14284,
            "name": "UFC 324: Gaethje vs. Pimblett",
            "tag": "Paramount+",
            "poster": "https://ppv.to/assets/thumb/dfe08bb48f4502d771b895d499d8ca10-thumbnail.jpg",
            "blurhash": "L5BfIR0g01E5XSjHRjS100%K}@s*",
            "colors": [
              "#040404",
              "#615432"
            ],
            "uri_name": "ufc-324",
            "starts_at": 1769306400,
            "ends_at": 1769335200,
            "always_live": 0,
            "locale": "en",
            "category_name": "Combat Sports",
            "iframe": "https://embednow.top/embed/ufc-324",
            "viewers": "0",
            "substreams": [],
            "m3u8_url": "https://gg.poocloud.in/ufc/index.m3u8",
            "m3u8_extracted_at": "2025-12-04T02:17:55.428411"
          }
        ]
      },
      {
        "category": "Cricket",
        "id": 47,
        "always_live": false,
        "streams": [
          {
            "id": 14306,
            "name": "Australia vs. England",
            "tag": "TNT Sports",
            "poster": "https://ppv.to/assets/thumb/4de443b4bf25d8cd895f9892ed00451d-thumbnail.jpg",
            "blurhash": "L9A+,Y0*E1}.s.bDjZjc00^Kx[5X",
            "colors": [
              "#230023",
              "#230023"
            ],
            "uri_name": "cricket/2025/en-au/2nd-test",
            "starts_at": 1764817200,
            "ends_at": 1764849600,
            "always_live": 0,
            "locale": "en",
            "category_name": "Cricket",
            "iframe": "https://embednow.top/embed/cricket/2025/en-au/2nd-test",
            "viewers": "3",
            "substreams": [],
            "m3u8_url": "https://gg.poocloud.in/cricket/index.m3u8",
            "m3u8_extracted_at": "2025-12-04T02:17:57.661478"
          }
        ]
      },
      {
        "category": "Football",
        "id": 34,
        "always_live": false,
        "streams": [
          {
            "id": 14390,
            "name": "Manchester United vs. West Ham United",
            "tag": "Premier League",
            "poster": "https://ppv.to/assets/thumb/6a0b314c42279f6bf01a5262247901e5-thumbnail.jpg",
            "blurhash": "LIFWFO|YR5j^oLayj[j[0fF2tloI",
            "colors": [
              "#d72a1c",
              "#79263a"
            ],
            "uri_name": "epl/2025-12-04/mun-whu",
            "starts_at": 1764878400,
            "ends_at": 1764887400,
            "always_live": 0,
            "locale": "en",
            "category_name": "Football",
            "iframe": "https://embednow.top/embed/epl/2025-12-04/mun-whu",
            "viewers": "0",
            "substreams": [],
            "m3u8_url": "https://gg.poocloud.in/epl_mun/index.m3u8",
            "m3u8_extracted_at": "2025-12-04T02:17:59.648074"
          },
          {
            "id": 14431,
            "name": "Brest vs. AS Monaco",
            "tag": "Ligue 1",
            "poster": "https://ppv.to/assets/thumb/da3a18d1270ec1926f28fe1b64a64a5f-thumbnail.jpg",
            "blurhash": "L1IKxb008w?^,GjsofkC00?w?^D4",
            "colors": [
              "#cf0a11",
              "#d50133"
            ],
            "uri_name": "ligue-1/2025-12-05/brs-mco",
            "starts_at": 1764957600,
            "ends_at": 1764966600,
            "always_live": 0,
            "locale": "en",
            "category_name": "Football",
            "iframe": "https://embednow.top/embed/ligue-1/2025-12-05/brs-mco",
            "viewers": "0",
            "substreams": [],
            "m3u8_url": "https://gg.poocloud.in/ligue1_brs/index.m3u8",
            "m3u8_extracted_at": "2025-12-04T02:18:02.258739"
          },
          {
            "id": 14412,
            "name": "Mainz vs. Gladbach",
            "tag": "ESPN+",
            "poster": "https://ppv.to/assets/thumb/f6a585129153f4125a428a81af52b456-thumbnail.jpg",
            "blurhash": "L7Grb_+b00Kis:jtWBbH00GE~q#8",
            "colors": [
              "#7f030d",
              "#7f030d"
            ],
            "uri_name": "bundesliga/2025-12-05/m05-bmg",
            "starts_at": 1764963000,
            "ends_at": 1764972000,
            "always_live": 0,
            "locale": "en",
            "category_name": "Football",
            "iframe": "https://embednow.top/embed/bundesliga/2025-12-05/m05-bmg",
            "viewers": "0",
            "substreams": [],
            "m3u8_url": "https://gg.poocloud.in/bundesliga_m05/index.m3u8",
            "m3u8_extracted_at": "2025-12-04T02:18:03.628608"
          },
          {
            "id": 14432,
            "name": "LOSC vs. OM",
            "tag": "Ligue 1",
            "poster": "https://ppv.to/assets/thumb/1413d2759f17d798cc6e8026acb33d5d-thumbnail.jpg",
            "blurhash": "LMD+Pt_~wOwIWBjZj[fk00KQf*Sh",
            "colors": [
              "#e41b14",
              "#0f96d0"
            ],
            "uri_name": "ligue-1/2025-12-05/lil-mar",
            "starts_at": 1764964800,
            "ends_at": 1764973800,
            "always_live": 0,
            "locale": "en",
            "category_name": "Football",
            "iframe": "https://embednow.top/embed/ligue-1/2025-12-05/lil-mar",
            "viewers": "0",
            "substreams": [],
            "m3u8_url": "https://gg.poocloud.in/ligue1_lil/index.m3u8",
            "m3u8_extracted_at": "2025-12-04T02:18:05.140856"
          },
          {
            "id": 14446,
            "name": "Real Oviedo vs. RCD Mallorca",
            "tag": "LaLiga",
            "poster": "https://ppv.to/assets/thumb/caa8d416a236a3dcb3059952bd5d9b0d-thumbnail.jpg",
            "blurhash": "L6JqsP%g0KMdrrnhWBX900R4~CpJ",
            "colors": [
              "#992d2a",
              "#992d2a"
            ],
            "uri_name": "laliga/2025-12-05/ovi-mll",
            "starts_at": 1764964800,
            "ends_at": 1764973800,
            "always_live": 0,
            "locale": "en",
            "category_name": "Football",
            "iframe": "https://embednow.top/embed/laliga/2025-12-05/ovi-mll",
            "viewers": "0",
            "substreams": [],
            "m3u8_url": "https://gg.poocloud.in/ll_ovi/index.m3u8",
            "m3u8_extracted_at": "2025-12-04T02:18:06.892795"
          },
          {
            "id": 14394,
            "name": "Aston Villa vs. Arsenal",
            "tag": "Premier League",
            "poster": "https://ppv.to/assets/thumb/5669eb4d695b129543260e546460c3d9-thumbnail.jpg",
            "blurhash": "LOG@AbC,S5Sioej@j[a#0Kvgt7s+",
            "colors": [
              "#94c0e3",
              "#ee0107"
            ],
            "uri_name": "epl/2025-12-06/avl-ars",
            "starts_at": 1765024200,
            "ends_at": 1765033200,
            "always_live": 0,
            "locale": "en",
            "category_name": "Football",
            "iframe": "https://embednow.top/embed/epl/2025-12-06/avl-ars",
            "viewers": "0",
            "substreams": [],
            "m3u8_url": "https://gg.poocloud.in/epl_avl/index.m3u8",
            "m3u8_extracted_at": "2025-12-04T02:18:08.694491"
          },
          {
            "id": 14447,
            "name": "Villarreal CF vs. Getafe CF",
            "tag": "LaLiga",
            "poster": "https://ppv.to/assets/thumb/fd0b0ffd7a390b687758d2f9228f3c0d-thumbnail.jpg",
            "blurhash": "L5J5Ds#600O[xYocWBWX00Te~Wn2",
            "colors": [
              "#992d2a",
              "#992d2a"
            ],
            "uri_name": "laliga/2025-12-06/vil-get",
            "starts_at": 1765026000,
            "ends_at": 1765035000,
            "always_live": 0,
            "locale": "en",
            "category_name": "Football",
            "iframe": "https://embednow.top/embed/laliga/2025-12-06/vil-get",
            "viewers": "0",
            "substreams": [],
            "m3u8_url": "https://gg.poocloud.in/ll_vil/index.m3u8",
            "m3u8_extracted_at": "2025-12-04T02:18:10.236021"
          },
          {
            "id": 14421,
            "name": "Sassuolo vs. Fiorentina",
            "tag": "Serie A",
            "poster": "https://ppv.to/assets/thumb/635bd397f6e7f9fa0fa857712ffbd014-thumbnail.jpg",
            "blurhash": "L57eloE[00,|t8fkjYju00,{~qEb",
            "colors": [
              "#00379b",
              "#00379b"
            ],
            "uri_name": "serie-a/2025-12-06/sas-fio",
            "starts_at": 1765029600,
            "ends_at": 1765038600,
            "always_live": 0,
            "locale": "en",
            "category_name": "Football",
            "iframe": "https://embednow.top/embed/serie-a/2025-12-06/sas-fio",
            "viewers": "0",
            "substreams": [],
            "m3u8_url": "https://gg.poocloud.in/seriea_sas/index.m3u8",
            "m3u8_extracted_at": "2025-12-04T02:18:12.252564"
          },
          {
            "id": 14413,
            "name": "Heidenheim vs. Freiburg",
            "tag": "ESPN+",
            "poster": "https://ppv.to/assets/thumb/d865ea3b1e8ded2aab9d592e39802363-thumbnail.jpg",
            "blurhash": "L8GY=^w200XlkWS3WBso00Op~qrY",
            "colors": [
              "#7f030d",
              "#7f030d"
            ],
            "uri_name": "bundesliga/2025-12-06/hdh-scf",
            "starts_at": 1765031400,
            "ends_at": 1765040400,
            "always_live": 0,
            "locale": "en",
            "category_name": "Football",
            "iframe": "https://embednow.top/embed/bundesliga/2025-12-06/hdh-scf",
            "viewers": "0",
            "substreams": [],
            "m3u8_url": "https://gg.poocloud.in/bundesliga_hdh/index.m3u8",
            "m3u8_extracted_at": "2025-12-04T02:18:13.861737"
          },
          {
            "id": 14414,
            "name": "Augsburg vs. Leverkusen",
            "tag": "ESPN+",
            "poster": "https://ppv.to/assets/thumb/ebd6330a9e707f1c1b11f6b8e7a39a4b-thumbnail.jpg",
            "blurhash": "L8H9arxH00M{xbofWBWC00W:_Nt7",
            "colors": [
              "#7f030d",
              "#7f030d"
            ],
            "uri_name": "bundesliga/2025-12-06/fca-b04",
            "starts_at": 1765031400,
            "ends_at": 1765040400,
            "always_live": 0,
            "locale": "en",
            "category_name": "Football",
            "iframe": "https://embednow.top/embed/bundesliga/2025-12-06/fca-b04",
            "viewers": "0",
            "substreams": [],
            "m3u8_url": "https://gg.poocloud.in/bundesliga_fca/index.m3u8",
            "m3u8_extracted_at": "2025-12-04T02:18:16.050597"
          },
          {
            "id": 14415,
            "name": "Cologne vs. St. Pauli",
            "tag": "ESPN+",
            "poster": "https://ppv.to/assets/thumb/ed0ef226b271fca14eeea02729239dc0-thumbnail.jpg",
            "blurhash": "L7HI~VDj00-;oLWVWBj[00-;_NE1",
            "colors": [
              "#7f030d",
              "#7f030d"
            ],
            "uri_name": "bundesliga/2025-12-06/koe-stp",
            "starts_at": 1765031400,
            "ends_at": 1765040400,
            "always_live": 0,
            "locale": "en",
            "category_name": "Football",
            "iframe": "https://embednow.top/embed/bundesliga/2025-12-06/koe-stp",
            "viewers": "0",
            "substreams": [],
            "m3u8_url": "https://gg.poocloud.in/bundesliga_koe/index.m3u8",
            "m3u8_extracted_at": "2025-12-04T02:18:17.792973"
          },
          {
            "id": 14416,
            "name": "Stuttgart vs. Bayern",
            "tag": "ESPN+",
            "poster": "https://ppv.to/assets/thumb/0556df90068e70e28351bd888c3c9dec-thumbnail.jpg",
            "blurhash": "L7HSc?xA00Sk%3t7WBR%00S7~qr:",
            "colors": [
              "#7f030d",
              "#7f030d"
            ],
            "uri_name": "bundesliga/2025-12-06/vfb-mun",
            "starts_at": 1765031400,
            "ends_at": 1765040400,
            "always_live": 0,
            "locale": "en",
            "category_name": "Football",
            "iframe": "https://embednow.top/embed/bundesliga/2025-12-06/vfb-mun",
            "viewers": "0",
            "substreams": [],
            "m3u8_url": "https://gg.poocloud.in/bundesliga_vfb/index.m3u8",
            "m3u8_extracted_at": "2025-12-04T02:18:20.291825"
          },
          {
            "id": 14417,
            "name": "Wolfsburg vs. Union Berlin",
            "tag": "ESPN+",
            "poster": "https://ppv.to/assets/thumb/87dd44a5b56faf653a95e0de19a68cf8-thumbnail.jpg",
            "blurhash": "L7G?eouh00Z3xuofWBWB00h#~qYP",
            "colors": [
              "#7f030d",
              "#7f030d"
            ],
            "uri_name": "bundesliga/2025-12-06/wob-fcu",
            "starts_at": 1765031400,
            "ends_at": 1765040400,
            "always_live": 0,
            "locale": "en",
            "category_name": "Football",
            "iframe": "https://embednow.top/embed/bundesliga/2025-12-06/wob-fcu",
            "viewers": "0",
            "substreams": [],
            "m3u8_url": "https://gg.poocloud.in/bundesliga_wob/index.m3u8",
            "m3u8_extracted_at": "2025-12-04T02:18:22.094643"
          },
          {
            "id": 14393,
            "name": "Bournemouth vs. Chelsea",
            "tag": "Premier League",
            "poster": "https://ppv.to/assets/thumb/1078d5df2053b30575f47be015e1d96d-thumbnail.jpg",
            "blurhash": "LHC=V-{crE-AjZf6j[j[00OttkI;",
            "colors": [
              "#da281c",
              "#064592"
            ],
            "uri_name": "epl/2025-12-06/bou-che",
            "starts_at": 1765033200,
            "ends_at": 1765042200,
            "always_live": 0,
            "locale": "en",
            "category_name": "Football",
            "iframe": "https://embednow.top/embed/epl/2025-12-06/bou-che",
            "viewers": "1",
            "substreams": [],
            "m3u8_url": "https://gg.poocloud.in/epl_bou/index.m3u8",
            "m3u8_extracted_at": "2025-12-04T02:18:24.670718"
          },
          {
            "id": 14396,
            "name": "Everton vs. Nottingham Forest",
            "tag": "Premier League",
            "poster": "https://ppv.to/assets/thumb/5021abcd9df1a881c5df4f02b7aaf4ec-thumbnail.jpg",
            "blurhash": "L9ChdL1-v3OYWBkCofWB00|qyDjG",
            "colors": [
              "#003197",
              "#e43134"
            ],
            "uri_name": "epl/2025-12-06/eve-nfo",
            "starts_at": 1765033200,
            "ends_at": 1765042200,
            "always_live": 0,
            "locale": "en",
            "category_name": "Football",
            "iframe": "https://embednow.top/embed/epl/2025-12-06/eve-nfo",
            "viewers": "0",
            "substreams": [],
            "m3u8_url": "https://gg.poocloud.in/epl_eve/index.m3u8",
            "m3u8_extracted_at": "2025-12-04T02:18:27.373476"
          },
          {
            "id": 14399,
            "name": "Manchester City vs. Sunderland",
            "tag": "Premier League",
            "poster": "https://ppv.to/assets/thumb/95d441ba573d712a2fbb3c6e4055ecbf-thumbnail.jpg",
            "blurhash": "LPFz~qCmV]I=jZfkj[az0JrCt7xZ",
            "colors": [
              "#6caadb",
              "#ea162c"
            ],
            "uri_name": "epl/2025-12-06/mci-sun",
            "starts_at": 1765033200,
            "ends_at": 1765042200,
            "always_live": 0,
            "locale": "en",
            "category_name": "Football",
            "iframe": "https://embednow.top/embed/epl/2025-12-06/mci-sun",
            "viewers": "0",
            "substreams": [],
            "m3u8_url": "https://gg.poocloud.in/epl_mci/index.m3u8",
            "m3u8_extracted_at": "2025-12-04T02:18:29.165508"
          },
          {
            "id": 14400,
            "name": "Newcastle United vs. Burnley",
            "tag": "Premier League",
            "poster": "https://ppv.to/assets/thumb/4e437abd9a4efbdba0aaae051fbb1556-thumbnail.jpg",
            "blurhash": "L49P~G2l00wynNV?ofo#00,I~qOA",
            "colors": [
              "#251f21",
              "#6b1d45"
            ],
            "uri_name": "epl/2025-12-06/new-bur",
            "starts_at": 1765033200,
            "ends_at": 1765042200,
            "always_live": 0,
            "locale": "en",
            "category_name": "Football",
            "iframe": "https://embednow.top/embed/epl/2025-12-06/new-bur",
            "viewers": "0",
            "substreams": [],
            "m3u8_url": "https://gg.poocloud.in/epl_new/index.m3u8",
            "m3u8_extracted_at": "2025-12-04T02:18:31.286306"
          },
          {
            "id": 14401,
            "name": "Tottenham Hotspur vs. Brentford",
            "tag": "Premier League",
            "poster": "https://ppv.to/assets/thumb/7868227a5e29bd941fc4411c798e9712-thumbnail.jpg",
            "blurhash": "L9EK7s1izWF{aeWVofj[00}EyDv~",
            "colors": [
              "#152256",
              "#fd0100"
            ],
            "uri_name": "epl/2025-12-06/tot-bre",
            "starts_at": 1765033200,
            "ends_at": 1765042200,
            "always_live": 0,
            "locale": "en",
            "category_name": "Football",
            "iframe": "https://embednow.top/embed/epl/2025-12-06/tot-bre",
            "viewers": "0",
            "substreams": [],
            "m3u8_url": "https://gg.poocloud.in/epl_tot/index.m3u8",
            "m3u8_extracted_at": "2025-12-04T02:18:33.028441"
          },
          {
            "id": 14448,
            "name": "Deportivo Alavés vs. Real Sociedad",
            "tag": "LaLiga",
            "poster": "https://ppv.to/assets/thumb/294edd06aa0e9953d5b0405f45284851-thumbnail.jpg",
            "blurhash": "L5I.5XOv00v{v}bvWBjE00vx~WTL",
            "colors": [
              "#992d2a",
              "#992d2a"
            ],
            "uri_name": "laliga/2025-12-06/ala-rso",
            "starts_at": 1765034100,
            "ends_at": 1765043100,
            "always_live": 0,
            "locale": "en",
            "category_name": "Football",
            "iframe": "https://embednow.top/embed/laliga/2025-12-06/ala-rso",
            "viewers": "0",
            "substreams": [],
            "m3u8_url": "https://gg.poocloud.in/ll_ala/index.m3u8",
            "m3u8_extracted_at": "2025-12-04T02:18:52.297447"
          },
          {
            "id": 14433,
            "name": "FC Nantes vs. RC Lens",
            "tag": "Ligue 1",
            "poster": "https://ppv.to/assets/thumb/48732dc1b32893bece97876dd10c899a-thumbnail.jpg",
            "blurhash": "LJJig=?*b:x@oLj[fkay01M+oNRQ",
            "colors": [
              "#ffdb01",
              "#c41414"
            ],
            "uri_name": "ligue-1/2025-12-06/nan-len",
            "starts_at": 1765036800,
            "ends_at": 1765045800,
            "always_live": 0,
            "locale": "en",
            "category_name": "Football",
            "iframe": "https://embednow.top/embed/ligue-1/2025-12-06/nan-len",
            "viewers": "0",
            "substreams": [],
            "m3u8_url": "https://gg.poocloud.in/ligue1_nan/index.m3u8",
            "m3u8_extracted_at": "2025-12-04T02:18:54.962455"
          },
          {
            "id": 14422,
            "name": "Inter vs. Como",
            "tag": "Serie A",
            "poster": "https://ppv.to/assets/thumb/3dfc043e7e5f4e097520a98c631071ce-thumbnail.jpg",
            "blurhash": "L585N^en00o#t8afaej[00bb~qaK",
            "colors": [
              "#00379b",
              "#00379b"
            ],
            "uri_name": "serie-a/2025-12-06/int-com",
            "starts_at": 1765040400,
            "ends_at": 1765049400,
            "always_live": 0,
            "locale": "en",
            "category_name": "Football",
            "iframe": "https://embednow.top/embed/serie-a/2025-12-06/int-com",
            "viewers": "0",
            "substreams": [],
            "m3u8_url": "https://gg.poocloud.in/seriea_int/index.m3u8",
            "m3u8_extracted_at": "2025-12-04T02:18:57.241973"
          },
          {
            "id": 14398,
            "name": "Leeds United vs. Liverpool",
            "tag": "Premier League",
            "poster": "https://ppv.to/assets/thumb/29b31ab38297ee24816f570595f73271-thumbnail.jpg",
            "blurhash": "LIJFoD?*WR$~j@bGj[js02RCtSNb",
            "colors": [
              "#ffcc03",
              "#c5112c"
            ],
            "uri_name": "epl/2025-12-06/lee-liv",
            "starts_at": 1765042200,
            "ends_at": 1765051200,
            "always_live": 0,
            "locale": "en",
            "category_name": "Football",
            "iframe": "https://embednow.top/embed/epl/2025-12-06/lee-liv",
            "viewers": "0",
            "substreams": [],
            "m3u8_url": "https://gg.poocloud.in/epl_lee/index.m3u8",
            "m3u8_extracted_at": "2025-12-04T02:18:59.515735"
          },
          {
            "id": 14418,
            "name": "RB Leipzig vs. Frankfurt",
            "tag": "ESPN+",
            "poster": "https://ppv.to/assets/thumb/ac4357174c8f739bea6359d82e8e2e86-thumbnail.jpg",
            "blurhash": "L7HSQfEM00-Ut7j[WBa|00-A~qI;",
            "colors": [
              "#7f030d",
              "#7f030d"
            ],
            "uri_name": "bundesliga/2025-12-06/rbl-sge",
            "starts_at": 1765042200,
            "ends_at": 1765051200,
            "always_live": 0,
            "locale": "en",
            "category_name": "Football",
            "iframe": "https://embednow.top/embed/bundesliga/2025-12-06/rbl-sge",
            "viewers": "0",
            "substreams": [],
            "m3u8_url": "https://gg.poocloud.in/bundesliga_rbl/index.m3u8",
            "m3u8_extracted_at": "2025-12-04T02:19:01.817812"
          },
          {
            "id": 14449,
            "name": "Real Betis vs. FC Barcelona",
            "tag": "LaLiga",
            "poster": "https://ppv.to/assets/thumb/06a62ae2e0572f19807e7d8b9bf90295-thumbnail.jpg",
            "blurhash": "L5JEh+tl00VY$gRkWBoz00VY~DpI",
            "colors": [
              "#992d2a",
              "#992d2a"
            ],
            "uri_name": "laliga/2025-12-06/bet-bar",
            "starts_at": 1765042200,
            "ends_at": 1765051200,
            "always_live": 0,
            "locale": "en",
            "category_name": "Football",
            "iframe": "https://embednow.top/embed/laliga/2025-12-06/bet-bar",
            "viewers": "0",
            "substreams": [],
            "m3u8_url": "https://gg.poocloud.in/ll_bet/index.m3u8",
            "m3u8_extracted_at": "2025-12-04T02:19:03.893046"
          },
          {
            "id": 14434,
            "name": "Toulouse FC vs. Strasbourg",
            "tag": "Ligue 1",
            "poster": "https://ppv.to/assets/thumb/3c71d4bcc20a3443d471d2cbe82ec70c-thumbnail.jpg",
            "blurhash": "L685pKY+I]$ckCaej[j[00u6%1NM",
            "colors": [
              "#3e2d59",
              "#039ee1"
            ],
            "uri_name": "ligue-1/2025-12-06/tou-sbg",
            "starts_at": 1765044000,
            "ends_at": 1765053000,
            "always_live": 0,
            "locale": "en",
            "category_name": "Football",
            "iframe": "https://embednow.top/embed/ligue-1/2025-12-06/tou-sbg",
            "viewers": "0",
            "substreams": [],
            "m3u8_url": "https://gg.poocloud.in/ligue1_tou/index.m3u8",
            "m3u8_extracted_at": "2025-12-04T02:19:05.213303"
          },
          {
            "id": 14423,
            "name": "Hellas Verona vs. Atalanta",
            "tag": "Serie A",
            "poster": "https://ppv.to/assets/thumb/577c8321d773adeb49313409f28490d1-thumbnail.jpg",
            "blurhash": "L58X*n#h00Owo#oHaeWZ00J?~qv_",
            "colors": [
              "#00379b",
              "#00379b"
            ],
            "uri_name": "serie-a/2025-12-06/ver-ata",
            "starts_at": 1765050300,
            "ends_at": 1765059300,
            "always_live": 0,
            "locale": "en",
            "category_name": "Football",
            "iframe": "https://embednow.top/embed/serie-a/2025-12-06/ver-ata",
            "viewers": "0",
            "substreams": [],
            "m3u8_url": "https://gg.poocloud.in/seriea_ver/index.m3u8",
            "m3u8_extracted_at": "2025-12-04T02:19:06.787441"
          },
          {
            "id": 14450,
            "name": "Athletic Club vs. Atlético de Madrid",
            "tag": "LaLiga",
            "poster": "https://ppv.to/assets/thumb/6207097a5fed441ce86325220f11d371-thumbnail.jpg",
            "blurhash": "L5JXzl%f00IBtlt7aeRk00My~C%L",
            "colors": [
              "#992d2a",
              "#992d2a"
            ],
            "uri_name": "laliga/2025-12-06/ath-atm",
            "starts_at": 1765051200,
            "ends_at": 1765060200,
            "always_live": 0,
            "locale": "en",
            "category_name": "Football",
            "iframe": "https://embednow.top/embed/laliga/2025-12-06/ath-atm",
            "viewers": "0",
            "substreams": [],
            "m3u8_url": "https://gg.poocloud.in/ll_ath/index.m3u8",
            "m3u8_extracted_at": "2025-12-04T02:19:09.267670"
          },
          {
            "id": 14435,
            "name": "PSG vs. Rennes",
            "tag": "Ligue 1",
            "poster": "https://ppv.to/assets/thumb/57910f21e35c5297c74118d13f835c74-thumbnail.jpg",
            "blurhash": "L6C5MN3Y*}E%t7WVj[j[00{xcExF",
            "colors": [
              "#013f6e",
              "#d7261c"
            ],
            "uri_name": "ligue-1/2025-12-06/psg-ren",
            "starts_at": 1765051500,
            "ends_at": 1765060500,
            "always_live": 0,
            "locale": "en",
            "category_name": "Football",
            "iframe": "https://embednow.top/embed/ligue-1/2025-12-06/psg-ren",
            "viewers": "0",
            "substreams": [],
            "m3u8_url": "https://gg.poocloud.in/ligue1_psg/index.m3u8",
            "m3u8_extracted_at": "2025-12-04T02:19:12.251255"
          },
          {
            "id": 14424,
            "name": "Cremonese vs. Lecce",
            "tag": "Serie A",
            "poster": "https://ppv.to/assets/thumb/d2ceab95f93fb99dee613dd2cc79b72c-thumbnail.jpg",
            "blurhash": "L57-]]~B0057offAe.j;0058~q^i",
            "colors": [
              "#00379b",
              "#00379b"
            ],
            "uri_name": "serie-a/2025-12-07/cre-lec",
            "starts_at": 1765107000,
            "ends_at": 1765116000,
            "always_live": 0,
            "locale": "en",
            "category_name": "Football",
            "iframe": "https://embednow.top/embed/serie-a/2025-12-07/cre-lec",
            "viewers": "0",
            "substreams": [],
            "m3u8_url": "https://gg.poocloud.in/seriea_cre/index.m3u8",
            "m3u8_extracted_at": "2025-12-04T02:19:14.942408"
          },
          {
            "id": 14451,
            "name": "Elche CF vs. Girona FC",
            "tag": "LaLiga",
            "poster": "https://ppv.to/assets/thumb/f9cec717117b53c26bd33b56c573859b-thumbnail.jpg",
            "blurhash": "L5JqpPP700z@%Lt7WBV[00v*~CO;",
            "colors": [
              "#992d2a",
              "#992d2a"
            ],
            "uri_name": "laliga/2025-12-07/elc-gir",
            "starts_at": 1765112400,
            "ends_at": 1765121400,
            "always_live": 0,
            "locale": "en",
            "category_name": "Football",
            "iframe": "https://embednow.top/embed/laliga/2025-12-07/elc-gir",
            "viewers": "0",
            "substreams": [],
            "m3u8_url": "https://gg.poocloud.in/ll_elc/index.m3u8",
            "m3u8_extracted_at": "2025-12-04T02:19:17.256005"
          },
          {
            "id": 14395,
            "name": "Brighton and Hove Albion vs. West Ham United",
            "tag": "Premier League",
            "poster": "https://ppv.to/assets/thumb/f937c2f0a5397752dcbe10b47d3f2592-thumbnail.jpg",
            "blurhash": "LIAAOVT#MzM|j]WVj[j[00VXx[tR",
            "colors": [
              "#0158b7",
              "#78263c"
            ],
            "uri_name": "epl/2025-12-07/bha-whu",
            "starts_at": 1765116000,
            "ends_at": 1765125000,
            "always_live": 0,
            "locale": "en",
            "category_name": "Football",
            "iframe": "https://embednow.top/embed/epl/2025-12-07/bha-whu",
            "viewers": "0",
            "substreams": [],
            "m3u8_url": "https://gg.poocloud.in/epl_bha/index.m3u8",
            "m3u8_extracted_at": "2025-12-04T02:19:18.646660"
          },
          {
            "id": 14425,
            "name": "Cagliari vs. Roma",
            "tag": "Serie A",
            "poster": "https://ppv.to/assets/thumb/d3b12f0eba7712364e946cd36cd411dd-thumbnail.jpg",
            "blurhash": "L58#F0.900Mc%1f6jFoL00I9~qyE",
            "colors": [
              "#00379b",
              "#00379b"
            ],
            "uri_name": "serie-a/2025-12-07/cag-rom",
            "starts_at": 1765116000,
            "ends_at": 1765125000,
            "always_live": 0,
            "locale": "en",
            "category_name": "Football",
            "iframe": "https://embednow.top/embed/serie-a/2025-12-07/cag-rom",
            "viewers": "0",
            "substreams": [],
            "m3u8_url": "https://gg.poocloud.in/seriea_cag/index.m3u8",
            "m3u8_extracted_at": "2025-12-04T02:19:21.468906"
          },
          {
            "id": 14436,
            "name": "OGC Nice vs. Angers SCO",
            "tag": "Ligue 1",
            "poster": "https://ppv.to/assets/thumb/3610909c3db9fc013e364de921e0a18c-thumbnail.jpg",
            "blurhash": "LNCq[P}Fv~r?oLayjuj[0eI:bvbb",
            "colors": [
              "#d72229",
              "#000000"
            ],
            "uri_name": "ligue-1/2025-12-07/nic-anr",
            "starts_at": 1765116000,
            "ends_at": 1765125000,
            "always_live": 0,
            "locale": "en",
            "category_name": "Football",
            "iframe": "https://embednow.top/embed/ligue-1/2025-12-07/nic-anr",
            "viewers": "0",
            "substreams": [],
            "m3u8_url": "https://gg.poocloud.in/ligue1_nic/index.m3u8",
            "m3u8_extracted_at": "2025-12-04T02:19:23.888860"
          },
          {
            "id": 14419,
            "name": "Hamburg vs. Bremen",
            "tag": "ESPN+",
            "poster": "https://ppv.to/assets/thumb/44829ee3ffe2fedce3c5a6c46f5ceaa1-thumbnail.jpg",
            "blurhash": "L7GG6RgQ00r.t7fRWBfj00nL~qS*",
            "colors": [
              "#7f030d",
              "#7f030d"
            ],
            "uri_name": "bundesliga/2025-12-07/hsv-svw",
            "starts_at": 1765117800,
            "ends_at": 1765126800,
            "always_live": 0,
            "locale": "en",
            "category_name": "Football",
            "iframe": "https://embednow.top/embed/bundesliga/2025-12-07/hsv-svw",
            "viewers": "0",
            "substreams": [],
            "m3u8_url": "https://gg.poocloud.in/bundesliga_hsv/index.m3u8",
            "m3u8_extracted_at": "2025-12-04T02:19:25.516617"
          },
          {
            "id": 14452,
            "name": "Valencia CF vs. Sevilla FC",
            "tag": "LaLiga",
            "poster": "https://ppv.to/assets/thumb/fd1ca053224a859216a214a98e1e04a9-thumbnail.jpg",
            "blurhash": "L5JhE=R$01whkqR.WBs+00s=~CSc",
            "colors": [
              "#992d2a",
              "#992d2a"
            ],
            "uri_name": "laliga/2025-12-07/val-sev",
            "starts_at": 1765120500,
            "ends_at": 1765129500,
            "always_live": 0,
            "locale": "en",
            "category_name": "Football",
            "iframe": "https://embednow.top/embed/laliga/2025-12-07/val-sev",
            "viewers": "0",
            "substreams": [],
            "m3u8_url": "https://gg.poocloud.in/ll_val/index.m3u8",
            "m3u8_extracted_at": "2025-12-04T02:19:27.295781"
          },
          {
            "id": 14437,
            "name": "AJ Auxerre vs. FC Metz",
            "tag": "Ligue 1",
            "poster": "https://ppv.to/assets/thumb/f511cee16b9340132f3e08723c4c7ca0-thumbnail.jpg",
            "blurhash": "L79Gn377M#tmt7t7j[Rj00-4x[M_",
            "colors": [
              "#164092",
              "#720f14"
            ],
            "uri_name": "ligue-1/2025-12-07/aux-met",
            "starts_at": 1765124100,
            "ends_at": 1765133100,
            "always_live": 0,
            "locale": "en",
            "category_name": "Football",
            "iframe": "https://embednow.top/embed/ligue-1/2025-12-07/aux-met",
            "viewers": "0",
            "substreams": [],
            "m3u8_url": "https://gg.poocloud.in/ligue1_aux/index.m3u8",
            "m3u8_extracted_at": "2025-12-04T02:19:30.125479"
          },
          {
            "id": 14438,
            "name": "Havre AC vs. Paris FC",
            "tag": "Ligue 1",
            "poster": "https://ppv.to/assets/thumb/45ada1247817a1946668df63de739768-thumbnail.jpg",
            "blurhash": "LN98Mi%%X9o#ofayj[j[8^ROodae",
            "colors": [
              "#7abde7",
              "#090e2c"
            ],
            "uri_name": "ligue-1/2025-12-07/lhv-pfc",
            "starts_at": 1765124100,
            "ends_at": 1765133100,
            "always_live": 0,
            "locale": "en",
            "category_name": "Football",
            "iframe": "https://embednow.top/embed/ligue-1/2025-12-07/lhv-pfc",
            "viewers": "0",
            "substreams": [],
            "m3u8_url": "https://gg.poocloud.in/ligue1_lhv/index.m3u8",
            "m3u8_extracted_at": "2025-12-04T02:19:32.402381"
          },
          {
            "id": 14397,
            "name": "Fulham vs. Crystal Palace",
            "tag": "Premier League",
            "poster": "https://ppv.to/assets/thumb/d2fd18098a2cd0b50e2ededc0ef1c66a-thumbnail.jpg",
            "blurhash": "LTEMh5~os+xuazj@j[a}00IVofV@",
            "colors": [
              "#ffffff",
              "#1d448f"
            ],
            "uri_name": "epl/2025-12-07/ful-cry",
            "starts_at": 1765125000,
            "ends_at": 1765134000,
            "always_live": 0,
            "locale": "en",
            "category_name": "Football",
            "iframe": "https://embednow.top/embed/epl/2025-12-07/ful-cry",
            "viewers": "0",
            "substreams": [],
            "m3u8_url": "https://gg.poocloud.in/epl_ful/index.m3u8",
            "m3u8_extracted_at": "2025-12-04T02:19:35.473800"
          },
          {
            "id": 14420,
            "name": "Dortmund vs. Hoffenheim",
            "tag": "ESPN+",
            "poster": "https://ppv.to/assets/thumb/959087cd7e92edfadfc2b55e30c9426b-thumbnail.jpg",
            "blurhash": "L7G$@,$F00Eqa$s:WBR+00OK_N$a",
            "colors": [
              "#7f030d",
              "#7f030d"
            ],
            "uri_name": "bundesliga/2025-12-07/dor-tsg",
            "starts_at": 1765125000,
            "ends_at": 1765134000,
            "always_live": 0,
            "locale": "en",
            "category_name": "Football",
            "iframe": "https://embednow.top/embed/bundesliga/2025-12-07/dor-tsg",
            "viewers": "0",
            "substreams": [],
            "m3u8_url": "https://gg.poocloud.in/bundesliga_dor/index.m3u8",
            "m3u8_extracted_at": "2025-12-04T02:19:36.832187"
          },
          {
            "id": 14426,
            "name": "Lazio vs. Bologna",
            "tag": "Serie A",
            "poster": "https://ppv.to/assets/thumb/81402c0c3fe75b55bde6faff246b5c9e-thumbnail.jpg",
            "blurhash": "L57U}=b{00Vqt7s+adWY00Z~~qp0",
            "colors": [
              "#00379b",
              "#00379b"
            ],
            "uri_name": "serie-a/2025-12-07/laz-bol",
            "starts_at": 1765126800,
            "ends_at": 1765135800,
            "always_live": 0,
            "locale": "en",
            "category_name": "Football",
            "iframe": "https://embednow.top/embed/serie-a/2025-12-07/laz-bol",
            "viewers": "0",
            "substreams": [],
            "m3u8_url": "https://gg.poocloud.in/seriea_laz/index.m3u8",
            "m3u8_extracted_at": "2025-12-04T02:19:56.370262"
          },
          {
            "id": 14453,
            "name": "RCD Espanyol de Barcelona vs. Rayo Vallecano",
            "tag": "LaLiga",
            "poster": "https://ppv.to/assets/thumb/965746d397d42931b18a85b53975179f-thumbnail.jpg",
            "blurhash": "L5JhI0vN00Y3xWi_WBbc00cX~Cid",
            "colors": [
              "#992d2a",
              "#992d2a"
            ],
            "uri_name": "laliga/2025-12-07/esp-ray",
            "starts_at": 1765128600,
            "ends_at": 1765137600,
            "always_live": 0,
            "locale": "en",
            "category_name": "Football",
            "iframe": "https://embednow.top/embed/laliga/2025-12-07/esp-ray",
            "viewers": "0",
            "substreams": [],
            "m3u8_url": "https://gg.poocloud.in/ll_esp/index.m3u8",
            "m3u8_extracted_at": "2025-12-04T02:19:59.202231"
          },
          {
            "id": 14427,
            "name": "Napoli vs. Juventus",
            "tag": "Serie A",
            "poster": "https://ppv.to/assets/thumb/1ec6366647755f299eef3bf02abba79e-thumbnail.jpg",
            "blurhash": "L57y3]Gt00zrtSWBe.oe00z;_NP9",
            "colors": [
              "#00379b",
              "#00379b"
            ],
            "uri_name": "serie-a/2025-12-07/nap-juv",
            "starts_at": 1765136700,
            "ends_at": 1765145700,
            "always_live": 0,
            "locale": "en",
            "category_name": "Football",
            "iframe": "https://embednow.top/embed/serie-a/2025-12-07/nap-juv",
            "viewers": "0",
            "substreams": [],
            "m3u8_url": "https://gg.poocloud.in/seriea_nap/index.m3u8",
            "m3u8_extracted_at": "2025-12-04T02:20:00.723188"
          },
          {
            "id": 14439,
            "name": "FC Lorient vs. OL",
            "tag": "Ligue 1",
            "poster": "https://ppv.to/assets/thumb/3af6418d01a026864cc8517c3cbe9f15-thumbnail.jpg",
            "blurhash": "LJEUv5|nw3-Ut7ayjtj[00OtbuIp",
            "colors": [
              "#ea750e",
              "#1022a8"
            ],
            "uri_name": "ligue-1/2025-12-07/lor-lyn",
            "starts_at": 1765136700,
            "ends_at": 1765145700,
            "always_live": 0,
            "locale": "en",
            "category_name": "Football",
            "iframe": "https://embednow.top/embed/ligue-1/2025-12-07/lor-lyn",
            "viewers": "0",
            "substreams": [],
            "m3u8_url": "https://gg.poocloud.in/ligue1_lor/index.m3u8",
            "m3u8_extracted_at": "2025-12-04T02:20:03.169020"
          },
          {
            "id": 14454,
            "name": "Real Madrid vs. Celta",
            "tag": "LaLiga",
            "poster": "https://ppv.to/assets/thumb/7474a99937f923382d44be84c63d9f57-thumbnail.jpg",
            "blurhash": "L6JN|Ll60Kq{xaaKWBf,00ie~CX+",
            "colors": [
              "#992d2a",
              "#992d2a"
            ],
            "uri_name": "laliga/2025-12-07/rma-cel",
            "starts_at": 1765137600,
            "ends_at": 1765146600,
            "always_live": 0,
            "locale": "en",
            "category_name": "Football",
            "iframe": "https://embednow.top/embed/laliga/2025-12-07/rma-cel",
            "viewers": "0",
            "substreams": [],
            "m3u8_url": "https://gg.poocloud.in/ll_rma/index.m3u8",
            "m3u8_extracted_at": "2025-12-04T02:20:04.911171"
          },
          {
            "id": 14428,
            "name": "Pisa vs. Parma",
            "tag": "Serie A",
            "poster": "https://ppv.to/assets/thumb/a13c4b1d8e7ee5c155e89f1bbb3d0c39-thumbnail.jpg",
            "blurhash": "L67.9UD,00-.oyWFaeob00-n_NE2",
            "colors": [
              "#00379b",
              "#00379b"
            ],
            "uri_name": "serie-a/2025-12-08/pis-par",
            "starts_at": 1765202400,
            "ends_at": 1765211400,
            "always_live": 0,
            "locale": "en",
            "category_name": "Football",
            "iframe": "https://embednow.top/embed/serie-a/2025-12-08/pis-par",
            "viewers": "0",
            "substreams": [],
            "m3u8_url": "https://gg.poocloud.in/seriea_pis/index.m3u8",
            "m3u8_extracted_at": "2025-12-04T02:20:06.917687"
          },
          {
            "id": 14429,
            "name": "Udinese vs. Genoa",
            "tag": "Serie A",
            "poster": "https://ppv.to/assets/thumb/09b85654a26095331c96fa40460bbaa2-thumbnail.jpg",
            "blurhash": "L58#RSTf00#6x]Rje-t700VX~qTe",
            "colors": [
              "#00379b",
              "#00379b"
            ],
            "uri_name": "serie-a/2025-12-08/udi-gen",
            "starts_at": 1765213200,
            "ends_at": 1765222200,
            "always_live": 0,
            "locale": "en",
            "category_name": "Football",
            "iframe": "https://embednow.top/embed/serie-a/2025-12-08/udi-gen",
            "viewers": "0",
            "substreams": [],
            "m3u8_url": "https://gg.poocloud.in/seriea_udi/index.m3u8",
            "m3u8_extracted_at": "2025-12-04T02:20:08.868347"
          },
          {
            "id": 14430,
            "name": "Torino vs. Milan",
            "tag": "Serie A",
            "poster": "https://ppv.to/assets/thumb/3b54cae89856104933a92072d50fd292-thumbnail.jpg",
            "blurhash": "L58qqQ$_00IvxuxXe.Rn00N3~qxo",
            "colors": [
              "#00379b",
              "#00379b"
            ],
            "uri_name": "serie-a/2025-12-08/tor-mil",
            "starts_at": 1765223100,
            "ends_at": 1765232100,
            "always_live": 0,
            "locale": "en",
            "category_name": "Football",
            "iframe": "https://embednow.top/embed/serie-a/2025-12-08/tor-mil",
            "viewers": "0",
            "substreams": [],
            "m3u8_url": "https://gg.poocloud.in/seriea_tor/index.m3u8",
            "m3u8_extracted_at": "2025-12-04T02:20:10.209358"
          },
          {
            "id": 14402,
            "name": "Wolverhampton Wanderers vs. Manchester United",
            "tag": "Premier League",
            "poster": "https://ppv.to/assets/thumb/a8ea9ec9d74a54fef1834fddfec25473-thumbnail.jpg",
            "blurhash": "LCJh]M*CRN-On%fjj[jt03rGtmI[",
            "colors": [
              "#fcb913",
              "#d72a1a"
            ],
            "uri_name": "epl/2025-12-08/wol-mun",
            "starts_at": 1765224000,
            "ends_at": 1765233000,
            "always_live": 0,
            "locale": "en",
            "category_name": "Football",
            "iframe": "https://embednow.top/embed/epl/2025-12-08/wol-mun",
            "viewers": "0",
            "substreams": [],
            "m3u8_url": "https://gg.poocloud.in/epl_wol/index.m3u8",
            "m3u8_extracted_at": "2025-12-04T02:20:13.428131"
          },
          {
            "id": 14455,
            "name": "CA Osasuna vs. Levante UD",
            "tag": "LaLiga",
            "poster": "https://ppv.to/assets/thumb/b42268396da7f5d1a63ebe28b41385ee-thumbnail.jpg",
            "blurhash": "L5I-yY=x00ELs:n%WBSg00EM~C%2",
            "colors": [
              "#992d2a",
              "#992d2a"
            ],
            "uri_name": "laliga/2025-12-08/osa-lev",
            "starts_at": 1765224000,
            "ends_at": 1765233000,
            "always_live": 0,
            "locale": "en",
            "category_name": "Football",
            "iframe": "https://embednow.top/embed/laliga/2025-12-08/osa-lev",
            "viewers": "0",
            "substreams": [],
            "m3u8_url": "https://gg.poocloud.in/ll_osa/index.m3u8",
            "m3u8_extracted_at": "2025-12-04T02:20:15.379344"
          }
        ]
      },
      {
        "category": "Motorsports",
        "id": 35,
        "always_live": false,
        "streams": [
          {
            "id": 14372,
            "name": "Abu Dhabi Grand Prix - FP1",
            "tag": "Formula 1",
            "poster": "https://ppv.to/assets/thumb/872fb7fd7bc18d07bc42ed7eee3290f5-thumbnail.jpg",
            "blurhash": "L8AmrH00RP~qIAt7xuDiD%?v_39F",
            "colors": [
              "#15151d",
              "#15151d"
            ],
            "uri_name": "f1/2025/united-arab-emirates/fp1",
            "starts_at": 1764927000,
            "ends_at": 1764934200,
            "always_live": 0,
            "locale": "en",
            "category_name": "Motorsports",
            "iframe": "https://embednow.top/embed/f1/2025/united-arab-emirates/fp1",
            "viewers": "0",
            "substreams": [],
            "m3u8_url": "https://gg.poocloud.in/f1/index.m3u8",
            "m3u8_extracted_at": "2025-12-04T02:20:17.183556"
          },
          {
            "id": 14373,
            "name": "Abu Dhabi Grand Prix - FP2",
            "tag": "Formula 1",
            "poster": "https://ppv.to/assets/thumb/dcba7ff5908d374016964a7369ce3168-thumbnail.jpg",
            "blurhash": "L8AwC+00RP~qIAxaxuDiD%?v_39F",
            "colors": [
              "#15151d",
              "#15151d"
            ],
            "uri_name": "f1/2025/united-arab-emirates/fp2",
            "starts_at": 1764939600,
            "ends_at": 1764946800,
            "always_live": 0,
            "locale": "en",
            "category_name": "Motorsports",
            "iframe": "https://embednow.top/embed/f1/2025/united-arab-emirates/fp2",
            "viewers": "0",
            "substreams": [],
            "m3u8_url": "https://gg.poocloud.in/f1/index.m3u8",
            "m3u8_extracted_at": "2025-12-04T02:20:19.750958"
          },
          {
            "id": 14374,
            "name": "Abu Dhabi Grand Prix - FP3",
            "tag": "Formula 1",
            "poster": "https://ppv.to/assets/thumb/e691fdcd52c74ad7a1f499ce87247c61-thumbnail.jpg",
            "blurhash": "L8AwC+00RP~qIAxaxuDiD%?v_39F",
            "colors": [
              "#15151d",
              "#15151d"
            ],
            "uri_name": "f1/2025/united-arab-emirates/fp3",
            "starts_at": 1765017000,
            "ends_at": 1765024200,
            "always_live": 0,
            "locale": "en",
            "category_name": "Motorsports",
            "iframe": "https://embednow.top/embed/f1/2025/united-arab-emirates/fp3",
            "viewers": "0",
            "substreams": [],
            "m3u8_url": "https://gg.poocloud.in/f1/index.m3u8",
            "m3u8_extracted_at": "2025-12-04T02:20:21.902462"
          },
          {
            "id": 14375,
            "name": "Abu Dhabi Grand Prix - Qualifying",
            "tag": "Formula 1",
            "poster": "https://ppv.to/assets/thumb/e53715e90a78c2d744d6ebad3cac4082-thumbnail.jpg",
            "blurhash": "L8AwC+00RP~qIAxaxuDiD%?v_39F",
            "colors": [
              "#15151d",
              "#15151d"
            ],
            "uri_name": "f1/2025/united-arab-emirates/qualifying",
            "starts_at": 1765029600,
            "ends_at": 1765036800,
            "always_live": 0,
            "locale": "en",
            "category_name": "Motorsports",
            "iframe": "https://embednow.top/embed/f1/2025/united-arab-emirates/qualifying",
            "viewers": "1",
            "substreams": [],
            "m3u8_url": "https://gg.poocloud.in/f1/index.m3u8",
            "m3u8_extracted_at": "2025-12-04T02:20:24.147971"
          },
          {
            "id": 14376,
            "name": "Abu Dhabi Grand Prix - Race",
            "tag": "Formula 1",
            "poster": "https://ppv.to/assets/thumb/d890eca4149c3753348ba502a664b75c-thumbnail.jpg",
            "blurhash": "L9AmrH00RP~qIUt7xuD%D%?b?b9F",
            "colors": [
              "#15151d",
              "#15151d"
            ],
            "uri_name": "f1/2025/united-arab-emirates/race",
            "starts_at": 1765112400,
            "ends_at": 1765123200,
            "always_live": 0,
            "locale": "en",
            "category_name": "Motorsports",
            "iframe": "https://embednow.top/embed/f1/2025/united-arab-emirates/race",
            "viewers": "0",
            "substreams": [],
            "m3u8_url": "https://gg.poocloud.in/f1/index.m3u8",
            "m3u8_extracted_at": "2025-12-04T02:20:26.381492"
          }
        ]
      },
      {
        "category": "Wrestling",
        "id": 38,
        "always_live": false,
        "streams": [
          {
            "id": 14379,
            "name": "AEW: Wednesday Night Dynamite",
            "tag": "TBS",
            "poster": "https://ppv.to/assets/thumb/b406ff9100d91b9210600260350246ff-thumbnail.jpg",
            "blurhash": "LHExeyNWV6M|$dbtRir?ZtWZ~Bwg",
            "colors": [
              "#152441",
              "#9c4ec5"
            ],
            "uri_name": "aew/dynamite/25-12-03",
            "starts_at": 1764810000,
            "ends_at": 1764820800,
            "always_live": 0,
            "locale": "en",
            "category_name": "Wrestling",
            "iframe": "https://embednow.top/embed/aew/dynamite/25-12-03",
            "viewers": "140",
            "substreams": [],
            "m3u8_url": "https://gg.poocloud.in/wrestling/index.m3u8",
            "m3u8_extracted_at": "2025-12-04T02:20:28.672796"
          },
          {
            "id": 14380,
            "name": "TNA: Impact",
            "tag": "AXS TV",
            "poster": "https://ppv.to/assets/thumb/78f581ee61589a76f6bcdeb095f95c12-thumbnail.jpg",
            "blurhash": "L6GFdr].0|t700EfGZR*3;J-{gt6",
            "colors": [
              "#030303",
              "#050505"
            ],
            "uri_name": "tna/impact/25-12-04",
            "starts_at": 1764896400,
            "ends_at": 1764907200,
            "always_live": 0,
            "locale": "en",
            "category_name": "Wrestling",
            "iframe": "https://embednow.top/embed/tna/impact/25-12-04",
            "viewers": "1",
            "substreams": [],
            "m3u8_url": "https://gg.poocloud.in/wrestling/index.m3u8",
            "m3u8_extracted_at": "2025-12-04T02:20:30.006549"
          },
          {
            "id": 14381,
            "name": "WWE: Friday Night Smackdown",
            "tag": "USA Network",
            "poster": "https://ppv.to/assets/thumb/ec7810b68fc39115ce3510bcf9687a63-thumbnail.jpg",
            "blurhash": "LF4ezej]M?s{kFkDf2fKIUWGxsfT",
            "colors": [
              "#001b65",
              "#0001b4"
            ],
            "uri_name": "wwe/smackdown/25-12-05",
            "starts_at": 1764982800,
            "ends_at": 1764993600,
            "always_live": 0,
            "locale": "en",
            "category_name": "Wrestling",
            "iframe": "https://embednow.top/embed/wwe/smackdown/25-12-05",
            "viewers": "0",
            "substreams": [],
            "m3u8_url": "https://gg.poocloud.in/wrestling/index.m3u8",
            "m3u8_extracted_at": "2025-12-04T02:20:32.175447"
          },
          {
            "id": 14382,
            "name": "AEW: Saturday Night Collision",
            "tag": "TNT",
            "poster": "https://ppv.to/assets/thumb/6e29b1bb679dd5133c85bbaadc2c4b13-thumbnail.jpg",
            "blurhash": "LDDk_9Na01of}mNwNMbF0TS#^cae",
            "colors": [
              "#210e10",
              "#160c0a"
            ],
            "uri_name": "aew/collision/25-12-06",
            "starts_at": 1765069200,
            "ends_at": 1765080000,
            "always_live": 0,
            "locale": "en",
            "category_name": "Wrestling",
            "iframe": "https://embednow.top/embed/aew/collision/25-12-06",
            "viewers": "3",
            "substreams": [],
            "m3u8_url": "https://gg.poocloud.in/wrestling/index.m3u8",
            "m3u8_extracted_at": "2025-12-04T02:20:35.292341"
          }
        ]
      },
      {
        "category": "24/7 Streams",
        "id": 14,
        "always_live": true,
        "streams": [
          {
            "id": 5112,
            "name": "24/7 South Park",
            "tag": "24/7 channel",
            "poster": "https://thumbs.poocloud.in/southpark/preview.jpg",
            "blurhash": "",
            "colors": [
              "#349150",
              "#510080"
            ],
            "uri_name": "247-south-park",
            "starts_at": 0,
            "ends_at": 0,
            "always_live": 1,
            "locale": "en",
            "category_name": "24/7 Streams",
            "iframe": "https://embednow.top/embed/247-south-park",
            "viewers": "30",
            "substreams": [],
            "m3u8_url": "https://gg.poocloud.in/southpark/index.m3u8",
            "m3u8_extracted_at": "2025-12-04T02:20:38.485561"
          },
          {
            "id": 3663,
            "name": "24/7 COWS",
            "tag": "24/7 channel",
            "poster": "https://ppv.to/assets/thumb/213d77252211e1926309f43b38263a4f-thumbnail.jpg",
            "blurhash": "LLHBJBIU.SIV~WD%.7n#%#nOoJi{",
            "colors": [
              "#8c797d",
              "#746353"
            ],
            "uri_name": "247-cows",
            "starts_at": 1737176400,
            "ends_at": 1740772800,
            "always_live": 1,
            "locale": "en",
            "category_name": "24/7 Streams",
            "iframe": "https://embednow.top/embed/247-cows",
            "viewers": "1",
            "substreams": [],
            "m3u8_url": "https://gg.poocloud.in/cows/index.m3u8",
            "m3u8_extracted_at": "2025-12-04T02:20:40.475498"
          },
          {
            "id": 8008,
            "name": "24/7 Family​​‌‌​‌​​‌​​‌‌‌‌‌‌‌‌‌​‌‌‌‌​‌​​‌‌‌ Guy",
            "tag": "24/7 channel",
            "poster": "https://thumbs.poocloud.in/familyguy/preview.jpg",
            "blurhash": "",
            "colors": [
              "#349150",
              "#510080"
            ],
            "uri_name": "247-family-guy",
            "starts_at": 1737187200,
            "ends_at": 1737190800,
            "always_live": 1,
            "locale": "en",
            "category_name": "24/7 Streams",
            "iframe": "https://embednow.top/embed/247-family-guy",
            "viewers": "32",
            "substreams": [],
            "m3u8_url": "https://gg.poocloud.in/familyguy/index.m3u8",
            "m3u8_extracted_at": "2025-12-04T02:20:42.739500"
          },
          {
            "id": 5191,
            "name": "24/7 The Simpsons",
            "tag": "24/7 channel",
            "poster": "https://thumbs.poocloud.in/thesimpsons/preview.jpg",
            "blurhash": "",
            "colors": [
              "#349150",
              "#510080"
            ],
            "uri_name": "247-the-simpsons",
            "starts_at": 1737196080,
            "ends_at": 1737196080,
            "always_live": 1,
            "locale": "en",
            "category_name": "24/7 Streams",
            "iframe": "https://embednow.top/embed/247-the-simpsons",
            "viewers": "10",
            "substreams": [],
            "m3u8_url": "https://gg.poocloud.in/thesimpsons/index.m3u8",
            "m3u8_extracted_at": "2025-12-04T02:20:55.881819"
          },
          {
            "id": 10681,
            "name": "Master stream test",
            "tag": "South Park/PPV",
            "poster": "https://ppv.to/assets/thumb/c7caf570cf3494e7f9ad1ae3f3122242-thumbnail.jpg",
            "blurhash": "L-K_5zRj~qt7?bj[xuofD%j[M{WB",
            "colors": [
              "#fffafe",
              "#fefcff"
            ],
            "uri_name": "master-stream-test-delete-12568",
            "starts_at": 1756101600,
            "ends_at": 1756116000,
            "always_live": 1,
            "locale": "en",
            "category_name": "24/7 Streams",
            "iframe": "https://embednow.top/embed/master-stream-test-delete-12568",
            "viewers": "1",
            "substreams": [
              {
                "id": 10682,
                "name": "Family Guy",
                "tag": "Family Guy/PPV",
                "locale": "en",
                "iframe": null
              }
            ],
            "m3u8_url": "https://5nhp186eg31fofnc.chinese-restaurant-api.site/v3/director/VE1ZGEyNDNkZWMyNzFjLWU2OWItNzFlNC00NWU5LTUyODY0MWIz/master.m3u8",
            "m3u8_extracted_at": "2025-12-04T02:20:57.787590"
          }
        ]
      }
    ]
  }
}