[
  {
    "date": "12-03-2026",
    "time": "18:45",
    "league": "Conference League",
    "team1": "AZ Alkmaar",
    "team2": "Sparta Prague",
    "channels": [
      [
        "37",
        "fr"
      ],
      [
        "141",
        "nl"
      ],
      [
        "167",
        "es"
      ]
    ],
    "iframes": [
      {
        "player1": "https://bolaloca.my/player/2/37",
        "player2": "https://bolaloca.my/player/3/37",
        "player3": "https://bolaloca.my/player/4/37",
        "channel": "CH37fr"
      },
      {
        "player1": "https://bolaloca.my/player/2/141",
        "player2": "https://bolaloca.my/player/3/141",
        "player3": "https://bolaloca.my/player/4/141",
        "channel": "CH141nl"
      },
      {
        "player1": "https://bolaloca.my/player/2/167",
        "player2": "https://bolaloca.my/player/3/167",
        "player3": "https://bolaloca.my/player/4/167",
        "channel": "CH167es"
      }
    ]
  },
  {
    "date": "12-03-2026",
    "time": "18:45",
    "league": "Conference League",
    "team1": "Lech Poznan",
    "team2": "Shakhtar Donetsk",
    "channels": [
      [
        "39",
        "fr"
      ],
      [
        "169",
        "es"
      ]
    ],
    "iframes": [
      {
        "player1": "https://bolaloca.my/player/2/39",
        "player2": "https://bolaloca.my/player/3/39",
        "player3": "https://bolaloca.my/player/4/39",
        "channel": "CH39fr"
      },
      {
        "player1": "https://bolaloca.my/player/2/169",
        "player2": "https://bolaloca.my/player/3/169",
        "player3": "https://bolaloca.my/player/4/169",
        "channel": "CH169es"
      }
    ]
  },
  {
    "date": "12-03-2026",
    "time": "18:45",
    "league": "Conference League",
    "team1": "Rijeka",
    "team2": "Strasbourg",
    "channels": [
      [
        "13",
        "fr"
      ],
      [
        "168",
        "es"
      ]
    ],
    "iframes": [
      {
        "player1": "https://bolaloca.my/player/2/13",
        "player2": "https://bolaloca.my/player/3/13",
        "player3": "https://bolaloca.my/player/4/13",
        "channel": "CH13fr"
      },
      {
        "player1": "https://bolaloca.my/player/2/168",
        "player2": "https://bolaloca.my/player/3/168",
        "player3": "https://bolaloca.my/player/4/168",
        "channel": "CH168es"
      }
    ]
  },
  {
    "date": "12-03-2026",
    "time": "18:45",
    "league": "Conference League",
    "team1": "Samsunspor",
    "team2": "Rayo Vallecano",
    "channels": [
      [
        "38",
        "fr"
      ],
      [
        "115",
        "de"
      ],
      [
        "162",
        "es"
      ]
    ],
    "iframes": [
      {
        "player1": "https://bolaloca.my/player/2/38",
        "player2": "https://bolaloca.my/player/3/38",
        "player3": "https://bolaloca.my/player/4/38",
        "channel": "CH38fr"
      },
      {
        "player1": "https://bolaloca.my/player/2/115",
        "player2": "https://bolaloca.my/player/3/115",
        "player3": "https://bolaloca.my/player/4/115",
        "channel": "CH115de"
      },
      {
        "player1": "https://bolaloca.my/player/2/162",
        "player2": "https://bolaloca.my/player/3/162",
        "player3": "https://bolaloca.my/player/4/162",
        "channel": "CH162es"
      }
    ]
  },
  {
    "date": "12-03-2026",
    "time": "18:45",
    "league": "Ligue Europa",
    "team1": "Multiplex Ligue Europa/Ligue Conference",
    "team2": "",
    "channels": [
      [
        "14",
        "fr"
      ]
    ],
    "iframes": [
      {
        "player1": "https://bolaloca.my/player/2/14",
        "player2": "https://bolaloca.my/player/3/14",
        "player3": "https://bolaloca.my/player/4/14",
        "channel": "CH14fr"
      }
    ]
  },
  {
    "date": "12-03-2026",
    "time": "18:45",
    "league": "Ligue Europa",
    "team1": "Bologna",
    "team2": "AS Roma",
    "channels": [
      [
        "34",
        "fr"
      ],
      [
        "112",
        "de"
      ],
      [
        "131",
        "gb"
      ],
      [
        "138",
        "it"
      ],
      [
        "165",
        "es"
      ],
      [
        "68",
        "es"
      ],
      [
        "89",
        "es"
      ]
    ],
    "iframes": [
      {
        "player1": "https://bolaloca.my/player/2/34",
        "player2": "https://bolaloca.my/player/3/34",
        "player3": "https://bolaloca.my/player/4/34",
        "channel": "CH34fr"
      },
      {
        "player1": "https://bolaloca.my/player/2/112",
        "player2": "https://bolaloca.my/player/3/112",
        "player3": "https://bolaloca.my/player/4/112",
        "channel": "CH112de"
      },
      {
        "player1": "https://bolaloca.my/player/2/131",
        "player2": "https://bolaloca.my/player/3/131",
        "player3": "https://bolaloca.my/player/4/131",
        "channel": "CH131gb"
      },
      {
        "player1": "https://bolaloca.my/player/2/138",
        "player2": "https://bolaloca.my/player/3/138",
        "player3": "https://bolaloca.my/player/4/138",
        "channel": "CH138it"
      },
      {
        "player1": "https://bolaloca.my/player/2/165",
        "player2": "https://bolaloca.my/player/3/165",
        "player3": "https://bolaloca.my/player/4/165",
        "channel": "CH165es"
      },
      {
        "player1": "https://bolaloca.my/player/2/68",
        "player2": "https://bolaloca.my/player/3/68",
        "player3": "https://bolaloca.my/player/4/68",
        "channel": "CH68es"
      },
      {
        "player1": "https://bolaloca.my/player/2/89",
        "player2": "https://bolaloca.my/player/3/89",
        "player3": "https://bolaloca.my/player/4/89",
        "channel": "CH89es"
      }
    ]
  },
  {
    "date": "12-03-2026",
    "time": "18:45",
    "league": "Ligue Europa",
    "team1": "Lille",
    "team2": "Aston Villa",
    "channels": [
      [
        "12",
        "fr"
      ],
      [
        "113",
        "de"
      ],
      [
        "126",
        "gb"
      ],
      [
        "140",
        "it"
      ],
      [
        "166",
        "es"
      ],
      [
        "87",
        "es"
      ],
      [
        "100",
        "es"
      ]
    ],
    "iframes": [
      {
        "player1": "https://bolaloca.my/player/2/12",
        "player2": "https://bolaloca.my/player/3/12",
        "player3": "https://bolaloca.my/player/4/12",
        "channel": "CH12fr"
      },
      {
        "player1": "https://bolaloca.my/player/2/113",
        "player2": "https://bolaloca.my/player/3/113",
        "player3": "https://bolaloca.my/player/4/113",
        "channel": "CH113de"
      },
      {
        "player1": "https://bolaloca.my/player/2/126",
        "player2": "https://bolaloca.my/player/3/126",
        "player3": "https://bolaloca.my/player/4/126",
        "channel": "CH126gb"
      },
      {
        "player1": "https://bolaloca.my/player/2/140",
        "player2": "https://bolaloca.my/player/3/140",
        "player3": "https://bolaloca.my/player/4/140",
        "channel": "CH140it"
      },
      {
        "player1": "https://bolaloca.my/player/2/166",
        "player2": "https://bolaloca.my/player/3/166",
        "player3": "https://bolaloca.my/player/4/166",
        "channel": "CH166es"
      },
      {
        "player1": "https://bolaloca.my/player/2/87",
        "player2": "https://bolaloca.my/player/3/87",
        "player3": "https://bolaloca.my/player/4/87",
        "channel": "CH87es"
      },
      {
        "player1": "https://bolaloca.my/player/2/100",
        "player2": "https://bolaloca.my/player/3/100",
        "player3": "https://bolaloca.my/player/4/100",
        "channel": "CH100es"
      }
    ]
  },
  {
    "date": "12-03-2026",
    "time": "18:45",
    "league": "Ligue Europa",
    "team1": "Panathinaikos",
    "team2": "Betis",
    "channels": [
      [
        "36",
        "fr"
      ],
      [
        "114",
        "de"
      ],
      [
        "133",
        "gb"
      ],
      [
        "149",
        "gr"
      ],
      [
        "161",
        "es"
      ],
      [
        "91",
        "es"
      ]
    ],
    "iframes": [
      {
        "player1": "https://bolaloca.my/player/2/36",
        "player2": "https://bolaloca.my/player/3/36",
        "player3": "https://bolaloca.my/player/4/36",
        "channel": "CH36fr"
      },
      {
        "player1": "https://bolaloca.my/player/2/114",
        "player2": "https://bolaloca.my/player/3/114",
        "player3": "https://bolaloca.my/player/4/114",
        "channel": "CH114de"
      },
      {
        "player1": "https://bolaloca.my/player/2/133",
        "player2": "https://bolaloca.my/player/3/133",
        "player3": "https://bolaloca.my/player/4/133",
        "channel": "CH133gb"
      },
      {
        "player1": "https://bolaloca.my/player/2/149",
        "player2": "https://bolaloca.my/player/3/149",
        "player3": "https://bolaloca.my/player/4/149",
        "channel": "CH149gr"
      },
      {
        "player1": "https://bolaloca.my/player/2/161",
        "player2": "https://bolaloca.my/player/3/161",
        "player3": "https://bolaloca.my/player/4/161",
        "channel": "CH161es"
      },
      {
        "player1": "https://bolaloca.my/player/2/91",
        "player2": "https://bolaloca.my/player/3/91",
        "player3": "https://bolaloca.my/player/4/91",
        "channel": "CH91es"
      }
    ]
  },
  {
    "date": "12-03-2026",
    "time": "18:45",
    "league": "Ligue Europa",
    "team1": "Stuttgart",
    "team2": "FC Porto",
    "channels": [
      [
        "35",
        "fr"
      ],
      [
        "116",
        "de"
      ],
      [
        "132",
        "gb"
      ],
      [
        "142",
        "nl"
      ],
      [
        "144",
        "pt"
      ],
      [
        "164",
        "es"
      ],
      [
        "90",
        "es"
      ]
    ],
    "iframes": [
      {
        "player1": "https://bolaloca.my/player/2/35",
        "player2": "https://bolaloca.my/player/3/35",
        "player3": "https://bolaloca.my/player/4/35",
        "channel": "CH35fr"
      },
      {
        "player1": "https://bolaloca.my/player/2/116",
        "player2": "https://bolaloca.my/player/3/116",
        "player3": "https://bolaloca.my/player/4/116",
        "channel": "CH116de"
      },
      {
        "player1": "https://bolaloca.my/player/2/132",
        "player2": "https://bolaloca.my/player/3/132",
        "player3": "https://bolaloca.my/player/4/132",
        "channel": "CH132gb"
      },
      {
        "player1": "https://bolaloca.my/player/2/142",
        "player2": "https://bolaloca.my/player/3/142",
        "player3": "https://bolaloca.my/player/4/142",
        "channel": "CH142nl"
      },
      {
        "player1": "https://bolaloca.my/player/2/144",
        "player2": "https://bolaloca.my/player/3/144",
        "player3": "https://bolaloca.my/player/4/144",
        "channel": "CH144pt"
      },
      {
        "player1": "https://bolaloca.my/player/2/164",
        "player2": "https://bolaloca.my/player/3/164",
        "player3": "https://bolaloca.my/player/4/164",
        "channel": "CH164es"
      },
      {
        "player1": "https://bolaloca.my/player/2/90",
        "player2": "https://bolaloca.my/player/3/90",
        "player3": "https://bolaloca.my/player/4/90",
        "channel": "CH90es"
      }
    ]
  },
  {
    "date": "12-03-2026",
    "time": "19:00",
    "league": "EuroLeague",
    "team1": "Monaco",
    "team2": "Olympiacos",
    "channels": [
      [
        "65",
        "es"
      ]
    ],
    "iframes": [
      {
        "player1": "https://bolaloca.my/player/2/65",
        "player2": "https://bolaloca.my/player/3/65",
        "player3": "https://bolaloca.my/player/4/65",
        "channel": "CH65es"
      }
    ]
  },
  {
    "date": "12-03-2026",
    "time": "20:00",
    "league": "EuroLeague",
    "team1": "Dubai",
    "team2": "Baskonia",
    "channels": [
      [
        "62",
        "es"
      ]
    ],
    "iframes": [
      {
        "player1": "https://bolaloca.my/player/2/62",
        "player2": "https://bolaloca.my/player/3/62",
        "player3": "https://bolaloca.my/player/4/62",
        "channel": "CH62es"
      }
    ]
  },
  {
    "date": "12-03-2026",
    "time": "20:30",
    "league": "EuroLeague",
    "team1": "Bayern",
    "team2": "Anadolu Efes",
    "channels": [
      [
        "66",
        "es"
      ]
    ],
    "iframes": [
      {
        "player1": "https://bolaloca.my/player/2/66",
        "player2": "https://bolaloca.my/player/3/66",
        "player3": "https://bolaloca.my/player/4/66",
        "channel": "CH66es"
      }
    ]
  },
  {
    "date": "12-03-2026",
    "time": "20:45",
    "league": "EuroLeague",
    "team1": "Real Madrid",
    "team2": "Valencia",
    "channels": [
      [
        "55",
        "es"
      ]
    ],
    "iframes": [
      {
        "player1": "https://bolaloca.my/player/2/55",
        "player2": "https://bolaloca.my/player/3/55",
        "player3": "https://bolaloca.my/player/4/55",
        "channel": "CH55es"
      }
    ]
  },
  {
    "date": "12-03-2026",
    "time": "21:00",
    "league": "Conference League",
    "team1": "Celje",
    "team2": "AEK Athens",
    "channels": [
      [
        "38",
        "fr"
      ],
      [
        "150",
        "gr"
      ],
      [
        "168",
        "es"
      ],
      [
        "100",
        "es"
      ]
    ],
    "iframes": [
      {
        "player1": "https://bolaloca.my/player/2/38",
        "player2": "https://bolaloca.my/player/3/38",
        "player3": "https://bolaloca.my/player/4/38",
        "channel": "CH38fr"
      },
      {
        "player1": "https://bolaloca.my/player/2/150",
        "player2": "https://bolaloca.my/player/3/150",
        "player3": "https://bolaloca.my/player/4/150",
        "channel": "CH150gr"
      },
      {
        "player1": "https://bolaloca.my/player/2/168",
        "player2": "https://bolaloca.my/player/3/168",
        "player3": "https://bolaloca.my/player/4/168",
        "channel": "CH168es"
      },
      {
        "player1": "https://bolaloca.my/player/2/100",
        "player2": "https://bolaloca.my/player/3/100",
        "player3": "https://bolaloca.my/player/4/100",
        "channel": "CH100es"
      }
    ]
  },
  {
    "date": "12-03-2026",
    "time": "21:00",
    "league": "Conference League",
    "team1": "Crystal Palace",
    "team2": "AEK Larnaca",
    "channels": [
      [
        "13",
        "fr"
      ],
      [
        "113",
        "de"
      ],
      [
        "130",
        "gb"
      ],
      [
        "167",
        "es"
      ]
    ],
    "iframes": [
      {
        "player1": "https://bolaloca.my/player/2/13",
        "player2": "https://bolaloca.my/player/3/13",
        "player3": "https://bolaloca.my/player/4/13",
        "channel": "CH13fr"
      },
      {
        "player1": "https://bolaloca.my/player/2/113",
        "player2": "https://bolaloca.my/player/3/113",
        "player3": "https://bolaloca.my/player/4/113",
        "channel": "CH113de"
      },
      {
        "player1": "https://bolaloca.my/player/2/130",
        "player2": "https://bolaloca.my/player/3/130",
        "player3": "https://bolaloca.my/player/4/130",
        "channel": "CH130gb"
      },
      {
        "player1": "https://bolaloca.my/player/2/167",
        "player2": "https://bolaloca.my/player/3/167",
        "player3": "https://bolaloca.my/player/4/167",
        "channel": "CH167es"
      }
    ]
  },
  {
    "date": "12-03-2026",
    "time": "21:00",
    "league": "Conference League",
    "team1": "Fiorentina",
    "team2": "Rakow",
    "channels": [
      [
        "36",
        "fr"
      ],
      [
        "138",
        "it"
      ],
      [
        "166",
        "es"
      ]
    ],
    "iframes": [
      {
        "player1": "https://bolaloca.my/player/2/36",
        "player2": "https://bolaloca.my/player/3/36",
        "player3": "https://bolaloca.my/player/4/36",
        "channel": "CH36fr"
      },
      {
        "player1": "https://bolaloca.my/player/2/138",
        "player2": "https://bolaloca.my/player/3/138",
        "player3": "https://bolaloca.my/player/4/138",
        "channel": "CH138it"
      },
      {
        "player1": "https://bolaloca.my/player/2/166",
        "player2": "https://bolaloca.my/player/3/166",
        "player3": "https://bolaloca.my/player/4/166",
        "channel": "CH166es"
      }
    ]
  },
  {
    "date": "12-03-2026",
    "time": "21:00",
    "league": "Conference League",
    "team1": "Sigma Olomouc",
    "team2": "Mainz",
    "channels": [
      [
        "37",
        "fr"
      ],
      [
        "114",
        "de"
      ],
      [
        "169",
        "es"
      ]
    ],
    "iframes": [
      {
        "player1": "https://bolaloca.my/player/2/37",
        "player2": "https://bolaloca.my/player/3/37",
        "player3": "https://bolaloca.my/player/4/37",
        "channel": "CH37fr"
      },
      {
        "player1": "https://bolaloca.my/player/2/114",
        "player2": "https://bolaloca.my/player/3/114",
        "player3": "https://bolaloca.my/player/4/114",
        "channel": "CH114de"
      },
      {
        "player1": "https://bolaloca.my/player/2/169",
        "player2": "https://bolaloca.my/player/3/169",
        "player3": "https://bolaloca.my/player/4/169",
        "channel": "CH169es"
      }
    ]
  },
  {
    "date": "12-03-2026",
    "time": "21:00",
    "league": "Copa De La Reina",
    "team1": "Badalona W",
    "team2": "Barcelona W",
    "channels": [
      [
        "71",
        "es"
      ]
    ],
    "iframes": [
      {
        "player1": "https://bolaloca.my/player/2/71",
        "player2": "https://bolaloca.my/player/3/71",
        "player3": "https://bolaloca.my/player/4/71",
        "channel": "CH71es"
      }
    ]
  },
  {
    "date": "12-03-2026",
    "time": "21:00",
    "league": "EuroLeague",
    "team1": "Panathinaikos",
    "team2": "Zalgiris Kaunas",
    "channels": [
      [
        "67",
        "es"
      ]
    ],
    "iframes": [
      {
        "player1": "https://bolaloca.my/player/2/67",
        "player2": "https://bolaloca.my/player/3/67",
        "player3": "https://bolaloca.my/player/4/67",
        "channel": "CH67es"
      }
    ]
  },
  {
    "date": "12-03-2026",
    "time": "21:00",
    "league": "EuroLeague",
    "team1": "Paris",
    "team2": "Lyon-Villeurbanne",
    "channels": [
      [
        "19",
        "fr"
      ]
    ],
    "iframes": [
      {
        "player1": "https://bolaloca.my/player/2/19",
        "player2": "https://bolaloca.my/player/3/19",
        "player3": "https://bolaloca.my/player/4/19",
        "channel": "CH19fr"
      }
    ]
  },
  {
    "date": "12-03-2026",
    "time": "21:00",
    "league": "Ligue Europa",
    "team1": "Multiplex Ligue Europa/Ligue Conference",
    "team2": "",
    "channels": [
      [
        "14",
        "fr"
      ]
    ],
    "iframes": [
      {
        "player1": "https://bolaloca.my/player/2/14",
        "player2": "https://bolaloca.my/player/3/14",
        "player3": "https://bolaloca.my/player/4/14",
        "channel": "CH14fr"
      }
    ]
  },
  {
    "date": "12-03-2026",
    "time": "21:00",
    "league": "Ligue Europa",
    "team1": "Celta Vigo",
    "team2": "Lyon",
    "channels": [
      [
        "11",
        "fr"
      ],
      [
        "131",
        "gb"
      ],
      [
        "140",
        "it"
      ],
      [
        "141",
        "nl"
      ],
      [
        "161",
        "es"
      ],
      [
        "89",
        "es"
      ]
    ],
    "iframes": [
      {
        "player1": "https://bolaloca.my/player/2/11",
        "player2": "https://bolaloca.my/player/3/11",
        "player3": "https://bolaloca.my/player/4/11",
        "channel": "CH11fr"
      },
      {
        "player1": "https://bolaloca.my/player/2/131",
        "player2": "https://bolaloca.my/player/3/131",
        "player3": "https://bolaloca.my/player/4/131",
        "channel": "CH131gb"
      },
      {
        "player1": "https://bolaloca.my/player/2/140",
        "player2": "https://bolaloca.my/player/3/140",
        "player3": "https://bolaloca.my/player/4/140",
        "channel": "CH140it"
      },
      {
        "player1": "https://bolaloca.my/player/2/141",
        "player2": "https://bolaloca.my/player/3/141",
        "player3": "https://bolaloca.my/player/4/141",
        "channel": "CH141nl"
      },
      {
        "player1": "https://bolaloca.my/player/2/161",
        "player2": "https://bolaloca.my/player/3/161",
        "player3": "https://bolaloca.my/player/4/161",
        "channel": "CH161es"
      },
      {
        "player1": "https://bolaloca.my/player/2/89",
        "player2": "https://bolaloca.my/player/3/89",
        "player3": "https://bolaloca.my/player/4/89",
        "channel": "CH89es"
      }
    ]
  },
  {
    "date": "12-03-2026",
    "time": "21:00",
    "league": "Ligue Europa",
    "team1": "Ferencvaros",
    "team2": "Braga",
    "channels": [
      [
        "35",
        "fr"
      ],
      [
        "115",
        "de"
      ],
      [
        "133",
        "gb"
      ],
      [
        "165",
        "es"
      ],
      [
        "91",
        "es"
      ]
    ],
    "iframes": [
      {
        "player1": "https://bolaloca.my/player/2/35",
        "player2": "https://bolaloca.my/player/3/35",
        "player3": "https://bolaloca.my/player/4/35",
        "channel": "CH35fr"
      },
      {
        "player1": "https://bolaloca.my/player/2/115",
        "player2": "https://bolaloca.my/player/3/115",
        "player3": "https://bolaloca.my/player/4/115",
        "channel": "CH115de"
      },
      {
        "player1": "https://bolaloca.my/player/2/133",
        "player2": "https://bolaloca.my/player/3/133",
        "player3": "https://bolaloca.my/player/4/133",
        "channel": "CH133gb"
      },
      {
        "player1": "https://bolaloca.my/player/2/165",
        "player2": "https://bolaloca.my/player/3/165",
        "player3": "https://bolaloca.my/player/4/165",
        "channel": "CH165es"
      },
      {
        "player1": "https://bolaloca.my/player/2/91",
        "player2": "https://bolaloca.my/player/3/91",
        "player3": "https://bolaloca.my/player/4/91",
        "channel": "CH91es"
      }
    ]
  },
  {
    "date": "12-03-2026",
    "time": "21:00",
    "league": "Ligue Europa",
    "team1": "Genk",
    "team2": "Freiburg",
    "channels": [
      [
        "34",
        "fr"
      ],
      [
        "112",
        "de"
      ],
      [
        "116",
        "de"
      ],
      [
        "132",
        "gb"
      ],
      [
        "164",
        "es"
      ],
      [
        "90",
        "es"
      ]
    ],
    "iframes": [
      {
        "player1": "https://bolaloca.my/player/2/34",
        "player2": "https://bolaloca.my/player/3/34",
        "player3": "https://bolaloca.my/player/4/34",
        "channel": "CH34fr"
      },
      {
        "player1": "https://bolaloca.my/player/2/112",
        "player2": "https://bolaloca.my/player/3/112",
        "player3": "https://bolaloca.my/player/4/112",
        "channel": "CH112de"
      },
      {
        "player1": "https://bolaloca.my/player/2/116",
        "player2": "https://bolaloca.my/player/3/116",
        "player3": "https://bolaloca.my/player/4/116",
        "channel": "CH116de"
      },
      {
        "player1": "https://bolaloca.my/player/2/132",
        "player2": "https://bolaloca.my/player/3/132",
        "player3": "https://bolaloca.my/player/4/132",
        "channel": "CH132gb"
      },
      {
        "player1": "https://bolaloca.my/player/2/164",
        "player2": "https://bolaloca.my/player/3/164",
        "player3": "https://bolaloca.my/player/4/164",
        "channel": "CH164es"
      },
      {
        "player1": "https://bolaloca.my/player/2/90",
        "player2": "https://bolaloca.my/player/3/90",
        "player3": "https://bolaloca.my/player/4/90",
        "channel": "CH90es"
      }
    ]
  },
  {
    "date": "12-03-2026",
    "time": "21:00",
    "league": "Ligue Europa",
    "team1": "Nottingham",
    "team2": "Midtjylland",
    "channels": [
      [
        "12",
        "fr"
      ],
      [
        "126",
        "gb"
      ],
      [
        "139",
        "it"
      ],
      [
        "142",
        "nl"
      ],
      [
        "149",
        "gr"
      ],
      [
        "162",
        "es"
      ],
      [
        "68",
        "es"
      ],
      [
        "87",
        "es"
      ]
    ],
    "iframes": [
      {
        "player1": "https://bolaloca.my/player/2/12",
        "player2": "https://bolaloca.my/player/3/12",
        "player3": "https://bolaloca.my/player/4/12",
        "channel": "CH12fr"
      },
      {
        "player1": "https://bolaloca.my/player/2/126",
        "player2": "https://bolaloca.my/player/3/126",
        "player3": "https://bolaloca.my/player/4/126",
        "channel": "CH126gb"
      },
      {
        "player1": "https://bolaloca.my/player/2/139",
        "player2": "https://bolaloca.my/player/3/139",
        "player3": "https://bolaloca.my/player/4/139",
        "channel": "CH139it"
      },
      {
        "player1": "https://bolaloca.my/player/2/142",
        "player2": "https://bolaloca.my/player/3/142",
        "player3": "https://bolaloca.my/player/4/142",
        "channel": "CH142nl"
      },
      {
        "player1": "https://bolaloca.my/player/2/149",
        "player2": "https://bolaloca.my/player/3/149",
        "player3": "https://bolaloca.my/player/4/149",
        "channel": "CH149gr"
      },
      {
        "player1": "https://bolaloca.my/player/2/162",
        "player2": "https://bolaloca.my/player/3/162",
        "player3": "https://bolaloca.my/player/4/162",
        "channel": "CH162es"
      },
      {
        "player1": "https://bolaloca.my/player/2/68",
        "player2": "https://bolaloca.my/player/3/68",
        "player3": "https://bolaloca.my/player/4/68",
        "channel": "CH68es"
      },
      {
        "player1": "https://bolaloca.my/player/2/87",
        "player2": "https://bolaloca.my/player/3/87",
        "player3": "https://bolaloca.my/player/4/87",
        "channel": "CH87es"
      }
    ]
  },
  {
    "date": "12-03-2026",
    "time": "21:00",
    "league": "Torneo LPF",
    "team1": "Defensa y Justicia",
    "team2": "Central Cordoba",
    "channels": [
      [
        "75",
        "es"
      ]
    ],
    "iframes": [
      {
        "player1": "https://bolaloca.my/player/2/75",
        "player2": "https://bolaloca.my/player/3/75",
        "player3": "https://bolaloca.my/player/4/75",
        "channel": "CH75es"
      }
    ]
  },
  {
    "date": "12-03-2026",
    "time": "21:00",
    "league": "Torneo LPF",
    "team1": "Dep. Riestra",
    "team2": "Gimnasia Mendoza",
    "channels": [
      [
        "76",
        "es"
      ]
    ],
    "iframes": [
      {
        "player1": "https://bolaloca.my/player/2/76",
        "player2": "https://bolaloca.my/player/3/76",
        "player3": "https://bolaloca.my/player/4/76",
        "channel": "CH76es"
      }
    ]
  },
  {
    "date": "12-03-2026",
    "time": "22:45",
    "league": "Liga Mx Women",
    "team1": "Cruz Azul W",
    "team2": "Necaxa W",
    "channels": [
      [
        "158",
        "es"
      ]
    ],
    "iframes": [
      {
        "player1": "https://bolaloca.my/player/2/158",
        "player2": "https://bolaloca.my/player/3/158",
        "player3": "https://bolaloca.my/player/4/158",
        "channel": "CH158es"
      }
    ]
  },
  {
    "date": "12-03-2026",
    "time": "23:15",
    "league": "Torneo LPF",
    "team1": "Estudiantes Rio Cuarto",
    "team2": "Belgrano",
    "channels": [
      [
        "76",
        "es"
      ]
    ],
    "iframes": [
      {
        "player1": "https://bolaloca.my/player/2/76",
        "player2": "https://bolaloca.my/player/3/76",
        "player3": "https://bolaloca.my/player/4/76",
        "channel": "CH76es"
      }
    ]
  },
  {
    "date": "12-03-2026",
    "time": "23:15",
    "league": "Torneo LPF",
    "team1": "Talleres Cordoba",
    "team2": "Instituto",
    "channels": [
      [
        "75",
        "es"
      ]
    ],
    "iframes": [
      {
        "player1": "https://bolaloca.my/player/2/75",
        "player2": "https://bolaloca.my/player/3/75",
        "player3": "https://bolaloca.my/player/4/75",
        "channel": "CH75es"
      }
    ]
  },
  {
    "date": "12-03-2026",
    "time": "23:30",
    "league": "Serie A Bresil",
    "team1": "Vasco",
    "team2": "Palmeiras",
    "channels": [
      [
        "55",
        "es"
      ],
      [
        "82",
        "es"
      ],
      [
        "162",
        "es"
      ]
    ],
    "iframes": [
      {
        "player1": "https://bolaloca.my/player/2/55",
        "player2": "https://bolaloca.my/player/3/55",
        "player3": "https://bolaloca.my/player/4/55",
        "channel": "CH55es"
      },
      {
        "player1": "https://bolaloca.my/player/2/82",
        "player2": "https://bolaloca.my/player/3/82",
        "player3": "https://bolaloca.my/player/4/82",
        "channel": "CH82es"
      },
      {
        "player1": "https://bolaloca.my/player/2/162",
        "player2": "https://bolaloca.my/player/3/162",
        "player3": "https://bolaloca.my/player/4/162",
        "channel": "CH162es"
      }
    ]
  },
  {
    "date": "13-03-2026",
    "time": "00:00",
    "league": "NBA",
    "team1": "Detroit Pistons",
    "team2": "Philadelphia 76ers",
    "channels": [
      [
        "175",
        "us"
      ]
    ],
    "iframes": [
      {
        "player1": "https://bolaloca.my/player/2/175",
        "player2": "https://bolaloca.my/player/3/175",
        "player3": "https://bolaloca.my/player/4/175",
        "channel": "CH175us"
      }
    ]
  },
  {
    "date": "13-03-2026",
    "time": "00:00",
    "league": "NBA",
    "team1": "Indiana Pacers",
    "team2": "Phoenix Suns",
    "channels": [
      [
        "176",
        "us"
      ]
    ],
    "iframes": [
      {
        "player1": "https://bolaloca.my/player/2/176",
        "player2": "https://bolaloca.my/player/3/176",
        "player3": "https://bolaloca.my/player/4/176",
        "channel": "CH176us"
      }
    ]
  },
  {
    "date": "13-03-2026",
    "time": "00:00",
    "league": "NBA",
    "team1": "Orlando Magic",
    "team2": "Washington Wizards",
    "channels": [
      [
        "177",
        "us"
      ]
    ],
    "iframes": [
      {
        "player1": "https://bolaloca.my/player/2/177",
        "player2": "https://bolaloca.my/player/3/177",
        "player3": "https://bolaloca.my/player/4/177",
        "channel": "CH177us"
      }
    ]
  },
  {
    "date": "13-03-2026",
    "time": "00:00",
    "league": "NHL",
    "team1": "Boston Bruins",
    "team2": "San Jose Sharks",
    "channels": [
      [
        "178",
        "us"
      ]
    ],
    "iframes": [
      {
        "player1": "https://bolaloca.my/player/2/178",
        "player2": "https://bolaloca.my/player/3/178",
        "player3": "https://bolaloca.my/player/4/178",
        "channel": "CH178us"
      }
    ]
  },
  {
    "date": "13-03-2026",
    "time": "00:00",
    "league": "NHL",
    "team1": "Buffalo Sabres",
    "team2": "Washington Capitals",
    "channels": [
      [
        "179",
        "us"
      ]
    ],
    "iframes": [
      {
        "player1": "https://bolaloca.my/player/2/179",
        "player2": "https://bolaloca.my/player/3/179",
        "player3": "https://bolaloca.my/player/4/179",
        "channel": "CH179us"
      }
    ]
  },
  {
    "date": "13-03-2026",
    "time": "00:00",
    "league": "NHL",
    "team1": "Carolina Hurricanes",
    "team2": "St. Louis Blues",
    "channels": [
      [
        "180",
        "us"
      ]
    ],
    "iframes": [
      {
        "player1": "https://bolaloca.my/player/2/180",
        "player2": "https://bolaloca.my/player/3/180",
        "player3": "https://bolaloca.my/player/4/180",
        "channel": "CH180us"
      }
    ]
  },
  {
    "date": "13-03-2026",
    "time": "00:00",
    "league": "NHL",
    "team1": "Florida Panthers",
    "team2": "Columbus Blue Jackets",
    "channels": [
      [
        "181",
        "us"
      ]
    ],
    "iframes": [
      {
        "player1": "https://bolaloca.my/player/2/181",
        "player2": "https://bolaloca.my/player/3/181",
        "player3": "https://bolaloca.my/player/4/181",
        "channel": "CH181us"
      }
    ]
  },
  {
    "date": "13-03-2026",
    "time": "00:00",
    "league": "NHL",
    "team1": "New Jersey Devils",
    "team2": "Calgary Flames",
    "channels": [
      [
        "182",
        "us"
      ]
    ],
    "iframes": [
      {
        "player1": "https://bolaloca.my/player/2/182",
        "player2": "https://bolaloca.my/player/3/182",
        "player3": "https://bolaloca.my/player/4/182",
        "channel": "CH182us"
      }
    ]
  },
  {
    "date": "13-03-2026",
    "time": "00:00",
    "league": "NHL",
    "team1": "Tampa Bay Lightning",
    "team2": "Detroit Red Wings",
    "channels": [
      [
        "183",
        "us"
      ]
    ],
    "iframes": [
      {
        "player1": "https://bolaloca.my/player/2/183",
        "player2": "https://bolaloca.my/player/3/183",
        "player3": "https://bolaloca.my/player/4/183",
        "channel": "CH183us"
      }
    ]
  },
  {
    "date": "13-03-2026",
    "time": "00:00",
    "league": "NHL",
    "team1": "Toronto Maple Leafs",
    "team2": "Anaheim Ducks",
    "channels": [
      [
        "184",
        "us"
      ]
    ],
    "iframes": [
      {
        "player1": "https://bolaloca.my/player/2/184",
        "player2": "https://bolaloca.my/player/3/184",
        "player3": "https://bolaloca.my/player/4/184",
        "channel": "CH184us"
      }
    ]
  },
  {
    "date": "13-03-2026",
    "time": "00:30",
    "league": "NBA",
    "team1": "Atlanta Hawks",
    "team2": "Brooklyn Nets",
    "channels": [
      [
        "185",
        "us"
      ]
    ],
    "iframes": [
      {
        "player1": "https://bolaloca.my/player/2/185",
        "player2": "https://bolaloca.my/player/3/185",
        "player3": "https://bolaloca.my/player/4/185",
        "channel": "CH185us"
      }
    ]
  },
  {
    "date": "13-03-2026",
    "time": "00:30",
    "league": "NBA",
    "team1": "Miami Heat",
    "team2": "Milwaukee Bucks",
    "channels": [
      [
        "186",
        "us"
      ]
    ],
    "iframes": [
      {
        "player1": "https://bolaloca.my/player/2/186",
        "player2": "https://bolaloca.my/player/3/186",
        "player3": "https://bolaloca.my/player/4/186",
        "channel": "CH186us"
      }
    ]
  },
  {
    "date": "13-03-2026",
    "time": "01:00",
    "league": "Concacaf Champions Cup",
    "team1": "FC Cincinnati",
    "team2": "Tigres UANL",
    "channels": [
      [
        "68",
        "es"
      ]
    ],
    "iframes": [
      {
        "player1": "https://bolaloca.my/player/2/68",
        "player2": "https://bolaloca.my/player/3/68",
        "player3": "https://bolaloca.my/player/4/68",
        "channel": "CH68es"
      }
    ]
  },
  {
    "date": "13-03-2026",
    "time": "01:00",
    "league": "Liga Mx Women",
    "team1": "Toluca W",
    "team2": "UNAM Pumas W",
    "channels": [
      [
        "159",
        "es"
      ]
    ],
    "iframes": [
      {
        "player1": "https://bolaloca.my/player/2/159",
        "player2": "https://bolaloca.my/player/3/159",
        "player3": "https://bolaloca.my/player/4/159",
        "channel": "CH159es"
      }
    ]
  },
  {
    "date": "13-03-2026",
    "time": "01:00",
    "league": "NBA",
    "team1": "Memphis Grizzlies",
    "team2": "Dallas Mavericks",
    "channels": [
      [
        "187",
        "us"
      ]
    ],
    "iframes": [
      {
        "player1": "https://bolaloca.my/player/2/187",
        "player2": "https://bolaloca.my/player/3/187",
        "player3": "https://bolaloca.my/player/4/187",
        "channel": "CH187us"
      }
    ]
  },
  {
    "date": "13-03-2026",
    "time": "01:00",
    "league": "NHL",
    "team1": "Dallas Stars",
    "team2": "Edmonton Oilers",
    "channels": [
      [
        "5",
        "fr"
      ],
      [
        "188",
        "us"
      ]
    ],
    "iframes": [
      {
        "player1": "https://bolaloca.my/player/2/5",
        "player2": "https://bolaloca.my/player/3/5",
        "player3": "https://bolaloca.my/player/4/5",
        "channel": "CH5fr"
      },
      {
        "player1": "https://bolaloca.my/player/2/188",
        "player2": "https://bolaloca.my/player/3/188",
        "player3": "https://bolaloca.my/player/4/188",
        "channel": "CH188us"
      }
    ]
  },
  {
    "date": "13-03-2026",
    "time": "01:00",
    "league": "NHL",
    "team1": "Minnesota Wild",
    "team2": "Philadelphia Flyers",
    "channels": [
      [
        "189",
        "us"
      ]
    ],
    "iframes": [
      {
        "player1": "https://bolaloca.my/player/2/189",
        "player2": "https://bolaloca.my/player/3/189",
        "player3": "https://bolaloca.my/player/4/189",
        "channel": "CH189us"
      }
    ]
  },
  {
    "date": "13-03-2026",
    "time": "01:00",
    "league": "NHL",
    "team1": "Winnipeg Jets",
    "team2": "New York Rangers",
    "channels": [
      [
        "190",
        "us"
      ]
    ],
    "iframes": [
      {
        "player1": "https://bolaloca.my/player/2/190",
        "player2": "https://bolaloca.my/player/3/190",
        "player3": "https://bolaloca.my/player/4/190",
        "channel": "CH190us"
      }
    ]
  },
  {
    "date": "13-03-2026",
    "time": "01:30",
    "league": "Copa Libertadores",
    "team1": "Ind. Medellin (Col)",
    "team2": "Juventud (Uru)",
    "channels": [
      [
        "69",
        "es"
      ],
      [
        "78",
        "es"
      ],
      [
        "79",
        "es"
      ],
      [
        "87",
        "es"
      ],
      [
        "97",
        "es"
      ]
    ],
    "iframes": [
      {
        "player1": "https://bolaloca.my/player/2/69",
        "player2": "https://bolaloca.my/player/3/69",
        "player3": "https://bolaloca.my/player/4/69",
        "channel": "CH69es"
      },
      {
        "player1": "https://bolaloca.my/player/2/78",
        "player2": "https://bolaloca.my/player/3/78",
        "player3": "https://bolaloca.my/player/4/78",
        "channel": "CH78es"
      },
      {
        "player1": "https://bolaloca.my/player/2/79",
        "player2": "https://bolaloca.my/player/3/79",
        "player3": "https://bolaloca.my/player/4/79",
        "channel": "CH79es"
      },
      {
        "player1": "https://bolaloca.my/player/2/87",
        "player2": "https://bolaloca.my/player/3/87",
        "player3": "https://bolaloca.my/player/4/87",
        "channel": "CH87es"
      },
      {
        "player1": "https://bolaloca.my/player/2/97",
        "player2": "https://bolaloca.my/player/3/97",
        "player3": "https://bolaloca.my/player/4/97",
        "channel": "CH97es"
      }
    ]
  },
  {
    "date": "13-03-2026",
    "time": "01:30",
    "league": "Serie A Bresil",
    "team1": "Gremio",
    "team2": "Bragantino",
    "channels": [
      [
        "82",
        "es"
      ],
      [
        "84",
        "es"
      ]
    ],
    "iframes": [
      {
        "player1": "https://bolaloca.my/player/2/82",
        "player2": "https://bolaloca.my/player/3/82",
        "player3": "https://bolaloca.my/player/4/82",
        "channel": "CH82es"
      },
      {
        "player1": "https://bolaloca.my/player/2/84",
        "player2": "https://bolaloca.my/player/3/84",
        "player3": "https://bolaloca.my/player/4/84",
        "channel": "CH84es"
      }
    ]
  },
  {
    "date": "13-03-2026",
    "time": "01:30",
    "league": "Torneo LPF",
    "team1": "Huracan",
    "team2": "River Plate",
    "channels": [
      [
        "75",
        "es"
      ],
      [
        "91",
        "es"
      ],
      [
        "161",
        "es"
      ]
    ],
    "iframes": [
      {
        "player1": "https://bolaloca.my/player/2/75",
        "player2": "https://bolaloca.my/player/3/75",
        "player3": "https://bolaloca.my/player/4/75",
        "channel": "CH75es"
      },
      {
        "player1": "https://bolaloca.my/player/2/91",
        "player2": "https://bolaloca.my/player/3/91",
        "player3": "https://bolaloca.my/player/4/91",
        "channel": "CH91es"
      },
      {
        "player1": "https://bolaloca.my/player/2/161",
        "player2": "https://bolaloca.my/player/3/161",
        "player3": "https://bolaloca.my/player/4/161",
        "channel": "CH161es"
      }
    ]
  },
  {
    "date": "13-03-2026",
    "time": "02:00",
    "league": "NBA",
    "team1": "San Antonio Spurs",
    "team2": "Denver Nuggets",
    "channels": [
      [
        "191",
        "us"
      ]
    ],
    "iframes": [
      {
        "player1": "https://bolaloca.my/player/2/191",
        "player2": "https://bolaloca.my/player/3/191",
        "player3": "https://bolaloca.my/player/4/191",
        "channel": "CH191us"
      }
    ]
  },
  {
    "date": "13-03-2026",
    "time": "02:00",
    "league": "NHL",
    "team1": "Utah Mammoth",
    "team2": "Chicago Blackhawks",
    "channels": [
      [
        "192",
        "us"
      ]
    ],
    "iframes": [
      {
        "player1": "https://bolaloca.my/player/2/192",
        "player2": "https://bolaloca.my/player/3/192",
        "player3": "https://bolaloca.my/player/4/192",
        "channel": "CH192us"
      }
    ]
  },
  {
    "date": "13-03-2026",
    "time": "02:30",
    "league": "NBA",
    "team1": "Oklahoma City Thunder",
    "team2": "Boston Celtics",
    "channels": [
      [
        "193",
        "us"
      ]
    ],
    "iframes": [
      {
        "player1": "https://bolaloca.my/player/2/193",
        "player2": "https://bolaloca.my/player/3/193",
        "player3": "https://bolaloca.my/player/4/193",
        "channel": "CH193us"
      }
    ]
  },
  {
    "date": "13-03-2026",
    "time": "03:00",
    "league": "Concacaf Champions Cup",
    "team1": "Vancouver Whitecaps",
    "team2": "Seattle Sounders",
    "channels": [
      [
        "68",
        "es"
      ]
    ],
    "iframes": [
      {
        "player1": "https://bolaloca.my/player/2/68",
        "player2": "https://bolaloca.my/player/3/68",
        "player3": "https://bolaloca.my/player/4/68",
        "channel": "CH68es"
      }
    ]
  },
  {
    "date": "13-03-2026",
    "time": "03:00",
    "league": "Liga Mx Women",
    "team1": "Tigres UANL W",
    "team2": "Santos Laguna W",
    "channels": [
      [
        "160",
        "es"
      ]
    ],
    "iframes": [
      {
        "player1": "https://bolaloca.my/player/2/160",
        "player2": "https://bolaloca.my/player/3/160",
        "player3": "https://bolaloca.my/player/4/160",
        "channel": "CH160es"
      }
    ]
  },
  {
    "date": "13-03-2026",
    "time": "03:00",
    "league": "NHL",
    "team1": "Seattle Kraken",
    "team2": "Colorado Avalanche",
    "channels": [
      [
        "194",
        "us"
      ]
    ],
    "iframes": [
      {
        "player1": "https://bolaloca.my/player/2/194",
        "player2": "https://bolaloca.my/player/3/194",
        "player3": "https://bolaloca.my/player/4/194",
        "channel": "CH194us"
      }
    ]
  },
  {
    "date": "13-03-2026",
    "time": "03:00",
    "league": "NHL",
    "team1": "Vancouver Canucks",
    "team2": "Nashville Predators",
    "channels": [
      [
        "195",
        "us"
      ]
    ],
    "iframes": [
      {
        "player1": "https://bolaloca.my/player/2/195",
        "player2": "https://bolaloca.my/player/3/195",
        "player3": "https://bolaloca.my/player/4/195",
        "channel": "CH195us"
      }
    ]
  },
  {
    "date": "13-03-2026",
    "time": "03:00",
    "league": "NHL",
    "team1": "Vegas Golden Knights",
    "team2": "Pittsburgh Penguins",
    "channels": [
      [
        "196",
        "us"
      ]
    ],
    "iframes": [
      {
        "player1": "https://bolaloca.my/player/2/196",
        "player2": "https://bolaloca.my/player/3/196",
        "player3": "https://bolaloca.my/player/4/196",
        "channel": "CH196us"
      }
    ]
  },
  {
    "date": "13-03-2026",
    "time": "03:30",
    "league": "NBA",
    "team1": "Los Angeles Lakers",
    "team2": "Chicago Bulls",
    "channels": [
      [
        "197",
        "us"
      ]
    ],
    "iframes": [
      {
        "player1": "https://bolaloca.my/player/2/197",
        "player2": "https://bolaloca.my/player/3/197",
        "player3": "https://bolaloca.my/player/4/197",
        "channel": "CH197us"
      }
    ]
  }
]